{
  "id": "set",
  "name": "Sets",
  "th": "เซต",
  "desc": "Set Fundamentals · Subsets · Power Sets",
  "glyph": "∪",
  "accent": "#2563eb",
  "parts": [
    {
      "id": "set-p1",
      "num": "PART 1",
      "name": "Set Fundamentals",
      "th": "Set Fundamentals",
      "cardCount": 4,
      "accent": "#2563eb",
      "gridHTML": "<div class=\"card\" data-accent=\"blue\">\n    <div class=\"card-head\">\n      <div class=\"eyebrow\">PART 1 · Set Fundamentals · 🔵 Concept</div>\n      <div class=\"title\">เขียนเซต</div>\n    </div>\n    <div class=\"trigger-box\">\n      <div class=\"ic\">🎯</div>\n      <div class=\"txt\">เห็นได้เป็นสมาชิกก่อน ถ้าบอกเงื่อนไขค่อยแปลกลับ</div>\n    </div>\n    <div class=\"section when\">\n      <div class=\"sec-head\"><span class=\"dot\"></span>👀 เมื่อเจอโจทย์แบบนี้</div>\n      <ul>\n      <li>ให้เซตสมาชิกมาโดยตรง เช่น \\(A=\\{1,2,3\\}\\)</li>\n      <li>ให้เงื่อนไขมา เช่น \\(A=\\{x\\mid x\\text{ เป็นจำนวนคู่ }<10\\}\\)</li>\n      </ul>\n    </div>\n    <div class=\"section how\">\n      <div class=\"sec-head\"><span class=\"dot\"></span>✅ วิธีคิด</div>\n      <ol>\n      <li>แบบแจกแจง: เขียนสมาชิกคั่นด้วยจุลภาค</li>\n      <li>แบบบอกเงื่อนไข: ใช้ \\(x\\mid\\) ตามด้วยเงื่อนไข</li>\n      <li>เช็กให้ชัดว่าเซตมีลำดับหรือไม่</li>\n      </ol>\n    </div>\n    <div class=\"section mistake\">\n      <div class=\"sec-head\"><span class=\"dot\"></span>❌ จุดที่พลาดบ่อย</div>\n      <ul>\n      <li>เขียนสมาชิกซ้ำโดยคิดว่าทำให้เซตใหญ่ขึ้น</li>\n      <li>สับสนระหว่างรายการสมาชิกกับเงื่อนไข</li>\n      </ul>\n    </div>\n    <div class=\"section hack\">\n      <div class=\"sec-head\"><span class=\"dot\"></span>🧠 เทคนิคจำ</div>\n      <div class=\"txt\">\"เห็นตัวอย่าง จดสมาชิก; เห็นเงื่อนไข แปลเป็นชุด\"</div>\n    </div>\n    <div class=\"section examtip\">\n      <div class=\"sec-head\"><span class=\"dot\"></span>🎯 ข้อสอบชอบออก</div>\n      <p>ข้อสอบชอบให้แปลงระหว่าง 2 แบบ แล้วถามว่าเซตไหนเหมือนกัน ต้องอ่านสมาชิกจริง ไม่ใช่ดูแค่หน้าตาโจทย์</p>\n    </div>\n    <div class=\"section checklist\">\n      <div class=\"sec-head\"><span class=\"dot\"></span>☑ Before You Submit</div>\n      <ul>\n      <li>มีสมาชิกครบหรือยัง</li>\n      <li>เงื่อนไขครอบคลุมทุกตัวหรือยัง</li>\n      </ul>\n    </div>\n    <div class=\"pagefoot\">SetTheoryRescueKit Rescue Kit · เปิดก่อนสอบ 10 นาที</div>\n  </div>\n\n\n  <div class=\"card\" data-accent=\"green\">\n    <div class=\"card-head\">\n      <div class=\"eyebrow\">PART 1 · Set Fundamentals · 🟠 Trigger</div>\n      <div class=\"title\">เป็นสมาชิก</div>\n    </div>\n    <div class=\"trigger-box\">\n      <div class=\"ic\">🎯</div>\n      <div class=\"txt\">ลอกมาทั้งก้อน คือสมาชิก; ไม่ตรงก้อน คือไม่ใช่</div>\n    </div>\n    <div class=\"section when\">\n      <div class=\"sec-head\"><span class=\"dot\"></span>👀 เมื่อเจอโจทย์แบบนี้</div>\n      <ul>\n      <li>ตรวจว่า \\(3\\in \\{1,2,3\\}\\) หรือไม่</li>\n      <li>ตรวจว่า \\(\\{3\\}\\in \\{1,2,\\{3\\}\\}\\) หรือไม่</li>\n      </ul>\n    </div>\n    <div class=\"section how\">\n      <div class=\"sec-head\"><span class=\"dot\"></span>✅ วิธีคิด</div>\n      <ol>\n      <li>มองซ้ายของสัญลักษณ์ก่อน</li>\n      <li>ถ้าเป็น \\(\\in\\) ให้หา 'ตัวนั้น' ในเซต</li>\n      <li>ถ้าไม่เจอพอดี ๆ ให้ตอบ \\(\\notin\\)</li>\n      </ol>\n    </div>\n    <div class=\"section mistake\">\n      <div class=\"sec-head\"><span class=\"dot\"></span>❌ จุดที่พลาดบ่อย</div>\n      <ul>\n      <li>เอาสิ่งที่เป็นเซตไปเทียบเป็นตัวเลข</li>\n      <li>เห็นวงเล็บแล้วคิดว่าเป็นสับเซตทันที</li>\n      </ul>\n    </div>\n    <div class=\"section hack\">\n      <div class=\"sec-head\"><span class=\"dot\"></span>🧠 เทคนิคจำ</div>\n      <div class=\"txt\">\"สมาชิกต้องเจอหน้าตาเดิม\"</div>\n    </div>\n    <div class=\"section examtip\">\n      <div class=\"sec-head\"><span class=\"dot\"></span>🎯 ข้อสอบชอบออก</div>\n      <p>ข้อถูก-ผิดมักหลอกด้วยวัตถุซ้อนเซต เช่น \\(\\{3\\}\\) กับ \\(\\{\\{3\\}\\}\\) ต้องดูชั้นปีกกาให้ดี</p>\n    </div>\n    <div class=\"section checklist\">\n      <div class=\"sec-head\"><span class=\"dot\"></span>☑ Before You Submit</div>\n      <ul>\n      <li>ซ้ายเป็นอะไร</li>\n      <li>ในเซตมีสิ่งนั้นแบบตรงตัวไหม</li>\n      </ul>\n    </div>\n    <div class=\"pagefoot\">SetTheoryRescueKit Rescue Kit · เปิดก่อนสอบ 10 นาที</div>\n  </div>\n\n\n  <div class=\"card\" data-accent=\"orange\">\n    <div class=\"card-head\">\n      <div class=\"eyebrow\">PART 1 · Set Fundamentals · 🔵 Concept</div>\n      <div class=\"title\">จำนวนสมาชิก</div>\n    </div>\n    <div class=\"trigger-box\">\n      <div class=\"ic\">🎯</div>\n      <div class=\"txt\">เซตจำกัดนับได้ เซตอนันต์นับไม่จบ เซตว่างไม่มีสักตัว</div>\n    </div>\n    <div class=\"section when\">\n      <div class=\"sec-head\"><span class=\"dot\"></span>👀 เมื่อเจอโจทย์แบบนี้</div>\n      <ul>\n      <li>นับสมาชิกของ \\(\\{1,2,3\\}\\)</li>\n      <li>พิจารณาเซตจำนวนคู่ \\(\\{2,4,6,\\dots\\}\\)</li>\n      </ul>\n    </div>\n    <div class=\"section how\">\n      <div class=\"sec-head\"><span class=\"dot\"></span>✅ วิธีคิด</div>\n      <ol>\n      <li>Finite: นับได้หมด</li>\n      <li>Infinite: มีต่อไม่สิ้นสุด</li>\n      <li>Empty set: ไม่มีสมาชิกเลย</li>\n      </ol>\n    </div>\n    <div class=\"section mistake\">\n      <div class=\"sec-head\"><span class=\"dot\"></span>❌ จุดที่พลาดบ่อย</div>\n      <ul>\n      <li>คิดว่าเซตว่างมีสมาชิกเป็นศูนย์ตัวเลข</li>\n      <li>นับสัญลักษณ์ซ้ำเป็นสมาชิกหลายตัว</li>\n      </ul>\n    </div>\n    <div class=\"section hack\">\n      <div class=\"sec-head\"><span class=\"dot\"></span>🧠 เทคนิคจำ</div>\n      <div class=\"txt\">\"นับได้จบ = finite\"</div>\n    </div>\n    <div class=\"section examtip\">\n      <div class=\"sec-head\"><span class=\"dot\"></span>🎯 ข้อสอบชอบออก</div>\n      <p>ข้อสอบชอบให้แยก \\(\\emptyset\\), เซตว่างกับ \\(\\{\\emptyset\\}\\) และเซตอนันต์จากตัวอย่างสั้น ๆ</p>\n    </div>\n    <div class=\"section checklist\">\n      <div class=\"sec-head\"><span class=\"dot\"></span>☑ Before You Submit</div>\n      <ul>\n      <li>มีสมาชิกครบหรือไม่</li>\n      <li>จบการนับได้ไหม</li>\n      </ul>\n    </div>\n    <div class=\"pagefoot\">SetTheoryRescueKit Rescue Kit · เปิดก่อนสอบ 10 นาที</div>\n  </div>\n\n\n  <div class=\"card\" data-accent=\"purple\">\n    <div class=\"card-head\">\n      <div class=\"eyebrow\">PART 1 · Set Fundamentals · 🟣 Exam Tip</div>\n      <div class=\"title\">เซตเท่ากับเทียบเท่า</div>\n    </div>\n    <div class=\"trigger-box\">\n      <div class=\"ic\">🎯</div>\n      <div class=\"txt\">เท่ากันต้องมีสมาชิกเหมือนกัน เทียบเท่าต้องมีจำนวนเท่ากัน</div>\n    </div>\n    <div class=\"section when\">\n      <div class=\"sec-head\"><span class=\"dot\"></span>👀 เมื่อเจอโจทย์แบบนี้</div>\n      <ul>\n      <li>ตรวจว่า \\(A=\\{1,2\\}\\) และ \\(B=\\{2,1\\}\\)</li>\n      <li>ตรวจว่า \\(A=\\{1,2\\}\\) และ \\(C=\\{a,b\\}\\)</li>\n      </ul>\n    </div>\n    <div class=\"section how\">\n      <div class=\"sec-head\"><span class=\"dot\"></span>✅ วิธีคิด</div>\n      <ol>\n      <li>\\(A=B\\): สมาชิกทุกตัวตรงกัน</li>\n      <li>\\(A\\sim B\\): จำนวนสมาชิกเท่ากัน</li>\n      <li>ไม่ต้องสนใจลำดับในเซต</li>\n      </ol>\n    </div>\n    <div class=\"section mistake\">\n      <div class=\"sec-head\"><span class=\"dot\"></span>❌ จุดที่พลาดบ่อย</div>\n      <ul>\n      <li>เอาเซตเทียบเท่ามาอ่านว่าเซตเท่ากัน</li>\n      <li>คิดว่าลำดับสมาชิกมีผล</li>\n      </ul>\n    </div>\n    <div class=\"section hack\">\n      <div class=\"sec-head\"><span class=\"dot\"></span>🧠 เทคนิคจำ</div>\n      <div class=\"txt\">\"เท่ากันคือเหมือนทุกตัว\"</div>\n    </div>\n    <div class=\"section examtip\">\n      <div class=\"sec-head\"><span class=\"dot\"></span>🎯 ข้อสอบชอบออก</div>\n      <p>ข้อสอบชอบถามความต่างของ \\(=\\) กับ \\(\\sim\\) โดยให้เซตหน้าตาไม่เหมือนกัน แต่จำนวนสมาชิกเท่ากัน</p>\n    </div>\n    <div class=\"section checklist\">\n      <div class=\"sec-head\"><span class=\"dot\"></span>☑ Before You Submit</div>\n      <ul>\n      <li>สมาชิกตรงกันทุกตัวไหม</li>\n      <li>จำนวนสมาชิกเท่ากันไหม</li>\n      </ul>\n    </div>\n    <div class=\"pagefoot\">SetTheoryRescueKit Rescue Kit · เปิดก่อนสอบ 10 นาที</div>\n  </div>"
    },
    {
      "id": "set-p2",
      "num": "PART 2",
      "name": "Subsets",
      "th": "Subsets",
      "cardCount": 5,
      "accent": "#2563eb",
      "gridHTML": "<div class=\"card\" data-accent=\"blue\">\n    <div class=\"card-head\">\n      <div class=\"eyebrow\">PART 2 · Subsets · 🔵 Concept</div>\n      <div class=\"title\">สับเซต</div>\n    </div>\n    <div class=\"trigger-box\">\n      <div class=\"ic\">🎯</div>\n      <div class=\"txt\">สับเซตต้องเอาทุกตัวในก้อนย่อย ไปอยู่ในก้อนใหญ่</div>\n    </div>\n    <div class=\"section when\">\n      <div class=\"sec-head\"><span class=\"dot\"></span>👀 เมื่อเจอโจทย์แบบนี้</div>\n      <ul>\n      <li>ตรวจว่า \\(\\{1,2\\}\\subset \\{1,2,3\\}\\)</li>\n      <li>ตรวจว่า \\(\\{1,4\\}\\subset \\{1,2,3\\}\\)</li>\n      </ul>\n    </div>\n    <div class=\"section how\">\n      <div class=\"sec-head\"><span class=\"dot\"></span>✅ วิธีคิด</div>\n      <ol>\n      <li>ดูสมาชิกทุกตัวของเซตซ้าย</li>\n      <li>เช็กว่าทุกตัวอยู่ในเซตขวาหรือไม่</li>\n      <li>ถ้าขาดแม้แต่ตัวเดียว = ไม่เป็นสับเซต</li>\n      </ol>\n    </div>\n    <div class=\"section mistake\">\n      <div class=\"sec-head\"><span class=\"dot\"></span>❌ จุดที่พลาดบ่อย</div>\n      <ul>\n      <li>เช็กแค่บางตัวแล้วรีบตอบ</li>\n      <li>สับสนสับเซตกับเป็นสมาชิก</li>\n      </ul>\n    </div>\n    <div class=\"section hack\">\n      <div class=\"sec-head\"><span class=\"dot\"></span>🧠 เทคนิคจำ</div>\n      <div class=\"txt\">\"ทุกตัวผ่าน = สับเซต\"</div>\n    </div>\n    <div class=\"section examtip\">\n      <div class=\"sec-head\"><span class=\"dot\"></span>🎯 ข้อสอบชอบออก</div>\n      <p>ข้อสอบมักใช้เซตที่มีเซตซ้อนอยู่ เพื่อหลอกให้คิดว่า \\(\\{3\\}\\) เป็นตัวเลขธรรมดา</p>\n    </div>\n    <div class=\"section checklist\">\n      <div class=\"sec-head\"><span class=\"dot\"></span>☑ Before You Submit</div>\n      <ul>\n      <li>ซ้ายเป็นก้อนหรือไม่</li>\n      <li>ทุกสมาชิกอยู่ในขวาหมดหรือยัง</li>\n      </ul>\n    </div>\n    <div class=\"pagefoot\">SetTheoryRescueKit Rescue Kit · เปิดก่อนสอบ 10 นาที</div>\n  </div>\n\n\n  <div class=\"card\" data-accent=\"green\">\n    <div class=\"card-head\">\n      <div class=\"eyebrow\">PART 2 · Subsets · 🔵 Concept</div>\n      <div class=\"title\">สับเซตแท้</div>\n    </div>\n    <div class=\"trigger-box\">\n      <div class=\"ic\">🎯</div>\n      <div class=\"txt\">สับเซตแท้คือสับเซตที่ไม่เท่ากันทั้งก้อน</div>\n    </div>\n    <div class=\"section when\">\n      <div class=\"sec-head\"><span class=\"dot\"></span>👀 เมื่อเจอโจทย์แบบนี้</div>\n      <ul>\n      <li>ตรวจว่า \\(A\\subset B\\) เมื่อ \\(A\\neq B\\)</li>\n      <li>ตรวจว่า \\(A\\subset A\\) ได้ไหม</li>\n      </ul>\n    </div>\n    <div class=\"section how\">\n      <div class=\"sec-head\"><span class=\"dot\"></span>✅ วิธีคิด</div>\n      <ol>\n      <li>เช็กก่อนว่าเป็นสับเซตหรือไม่</li>\n      <li>ถ้าเท่ากันทั้งชุด = ไม่ใช่สับเซตแท้</li>\n      <li>สับเซตแท้ต้องเล็กกว่าจริง</li>\n      </ol>\n    </div>\n    <div class=\"section mistake\">\n      <div class=\"sec-head\"><span class=\"dot\"></span>❌ จุดที่พลาดบ่อย</div>\n      <ul>\n      <li>คิดว่า \\(A\\subset A\\) เป็นสับเซตแท้</li>\n      <li>ลืมเงื่อนไขไม่เท่ากัน</li>\n      </ul>\n    </div>\n    <div class=\"section hack\">\n      <div class=\"sec-head\"><span class=\"dot\"></span>🧠 เทคนิคจำ</div>\n      <div class=\"txt\">\"แท้ต้องเล็กกว่า\"</div>\n    </div>\n    <div class=\"section examtip\">\n      <div class=\"sec-head\"><span class=\"dot\"></span>🎯 ข้อสอบชอบออก</div>\n      <p>ข้อสอบชอบออกเงื่อนไขแฝงว่าเท่ากันหรือไม่ ถ้าเซตเหมือนกันหมด ห้ามเรียกแท้</p>\n    </div>\n    <div class=\"section checklist\">\n      <div class=\"sec-head\"><span class=\"dot\"></span>☑ Before You Submit</div>\n      <ul>\n      <li>เป็นสับเซตก่อนหรือยัง</li>\n      <li>เท่ากันหรือยัง</li>\n      </ul>\n    </div>\n    <div class=\"pagefoot\">SetTheoryRescueKit Rescue Kit · เปิดก่อนสอบ 10 นาที</div>\n  </div>\n\n\n  <div class=\"card\" data-accent=\"orange\">\n    <div class=\"card-head\">\n      <div class=\"eyebrow\">PART 2 · Subsets · 🟠 Trigger</div>\n      <div class=\"title\">เซตว่างเป็นสับเซต</div>\n    </div>\n    <div class=\"trigger-box\">\n      <div class=\"ic\">🎯</div>\n      <div class=\"txt\">เซตว่างไม่มีตัวให้ขัดขืน จึงเป็นสับเซตของทุกเซต</div>\n    </div>\n    <div class=\"section when\">\n      <div class=\"sec-head\"><span class=\"dot\"></span>👀 เมื่อเจอโจทย์แบบนี้</div>\n      <ul>\n      <li>พิจารณา \\(\\emptyset\\subset A\\)</li>\n      <li>พิจารณา \\(\\emptyset\\subset \\emptyset\\)</li>\n      </ul>\n    </div>\n    <div class=\"section how\">\n      <div class=\"sec-head\"><span class=\"dot\"></span>✅ วิธีคิด</div>\n      <ol>\n      <li>จำกฎเหล็กทันที</li>\n      <li>ไม่ต้องไล่สมาชิก เพราะไม่มีสมาชิก</li>\n      <li>ใช้ได้กับทุกเซต</li>\n      </ol>\n    </div>\n    <div class=\"section mistake\">\n      <div class=\"sec-head\"><span class=\"dot\"></span>❌ จุดที่พลาดบ่อย</div>\n      <ul>\n      <li>คิดว่าเซตว่างไม่เกี่ยวกับสับเซต</li>\n      <li>สับสนระหว่าง \\(\\emptyset\\in A\\) กับ \\(\\emptyset\\subset A\\)</li>\n      </ul>\n    </div>\n    <div class=\"section hack\">\n      <div class=\"sec-head\"><span class=\"dot\"></span>🧠 เทคนิคจำ</div>\n      <div class=\"txt\">\"ว่าง = สับเซตเสมอ\"</div>\n    </div>\n    <div class=\"section examtip\">\n      <div class=\"sec-head\"><span class=\"dot\"></span>🎯 ข้อสอบชอบออก</div>\n      <p>ข้อสอบชอบเอา \\(\\emptyset\\) ไปหลอกในข้อถูก-ผิด ว่ามันอยู่ในเซตหรือเป็นสับเซต ต้องแยกให้ได้</p>\n    </div>\n    <div class=\"section checklist\">\n      <div class=\"sec-head\"><span class=\"dot\"></span>☑ Before You Submit</div>\n      <ul>\n      <li>เป็น \\(\\subset\\) ไหม</li>\n      <li>มีสมาชิกให้ตรวจหรือไม่</li>\n      </ul>\n    </div>\n    <div class=\"pagefoot\">SetTheoryRescueKit Rescue Kit · เปิดก่อนสอบ 10 นาที</div>\n  </div>\n\n\n  <div class=\"card\" data-accent=\"purple\">\n    <div class=\"card-head\">\n      <div class=\"eyebrow\">PART 2 · Subsets · 🟢 Formula</div>\n      <div class=\"title\">นับสับเซต</div>\n    </div>\n    <div class=\"trigger-box\">\n      <div class=\"ic\">🎯</div>\n      <div class=\"txt\">มีสมาชิก n ตัว สับเซตทั้งหมดคือสองยกกำลัง n</div>\n    </div>\n    <div class=\"section when\">\n      <div class=\"sec-head\"><span class=\"dot\"></span>👀 เมื่อเจอโจทย์แบบนี้</div>\n      <ul>\n      <li>เซตมี 3 สมาชิก ต้องการจำนวนสับเซต</li>\n      <li>เซตมี 5 สมาชิก ต้องการจำนวนสับเซตแท้</li>\n      </ul>\n    </div>\n    <div class=\"section how\">\n      <div class=\"sec-head\"><span class=\"dot\"></span>✅ วิธีคิด</div>\n      <ol>\n      <li>นับจำนวนสมาชิกของเซตก่อน</li>\n      <li>ใช้สูตร \\(2^n\\) สำหรับสับเซตทั้งหมด</li>\n      <li>สับเซตแท้ = \\(2^n-1\\)</li>\n      </ol>\n    </div>\n    <div class=\"section mistake\">\n      <div class=\"sec-head\"><span class=\"dot\"></span>❌ จุดที่พลาดบ่อย</div>\n      <ul>\n      <li>ลืมลบ 1 ตอนถามสับเซตแท้</li>\n      <li>นับสมาชิกผิดแล้วค่อยใส่สูตร</li>\n      </ul>\n    </div>\n    <div class=\"section hack\">\n      <div class=\"sec-head\"><span class=\"dot\"></span>🧠 เทคนิคจำ</div>\n      <div class=\"txt\">\"นับตัวก่อน ค่อยยกกำลัง\"</div>\n    </div>\n    <div class=\"section examtip\">\n      <div class=\"sec-head\"><span class=\"dot\"></span>🎯 ข้อสอบชอบออก</div>\n      <p>ข้อสอบชอบให้หาแบบเร็วจากจำนวนสมาชิก ไม่ได้ให้ไล่เขียนทุกสับเซต เพราะจะเสียเวลา</p>\n    </div>\n    <div class=\"section checklist\">\n      <div class=\"sec-head\"><span class=\"dot\"></span>☑ Before You Submit</div>\n      <ul>\n      <li>นับ \\(n\\) ถูกไหม</li>\n      <li>ถามทั้งหมดหรือแท้</li>\n      </ul>\n    </div>\n    <div class=\"pagefoot\">SetTheoryRescueKit Rescue Kit · เปิดก่อนสอบ 10 นาที</div>\n  </div>\n\n\n  <div class=\"card\" data-accent=\"blue\">\n    <div class=\"card-head\">\n      <div class=\"eyebrow\">PART 2 · Subsets · 🟣 Exam Tip</div>\n      <div class=\"title\">เงื่อนไขสับเซต</div>\n    </div>\n    <div class=\"trigger-box\">\n      <div class=\"ic\">🎯</div>\n      <div class=\"txt\">มีตัวบังคับ เอาออกก่อน ที่เหลือค่อยยกกำลัง</div>\n    </div>\n    <div class=\"section when\">\n      <div class=\"sec-head\"><span class=\"dot\"></span>👀 เมื่อเจอโจทย์แบบนี้</div>\n      <ul>\n      <li>นับสับเซตของ \\(A\\) ที่ต้องมี 1 แต่ไม่มี 2</li>\n      <li>นับสับเซตที่มีสมาชิกบังคับ 3 ตัวจากทั้งหมด 6 ตัว</li>\n      </ul>\n    </div>\n    <div class=\"section how\">\n      <div class=\"sec-head\"><span class=\"dot\"></span>✅ วิธีคิด</div>\n      <ol>\n      <li>แยกตัวบังคับออกก่อน</li>\n      <li>ตรึงตัวที่ต้องมีไว้</li>\n      <li>เหลือตัวอิสระกี่ตัว ใช้ \\(2^k\\)</li>\n      </ol>\n    </div>\n    <div class=\"section mistake\">\n      <div class=\"sec-head\"><span class=\"dot\"></span>❌ จุดที่พลาดบ่อย</div>\n      <ul>\n      <li>เอาตัวบังคับไปนับรวมกับอิสระ</li>\n      <li>ลืมตัดเงื่อนไขที่ห้ามออก</li>\n      </ul>\n    </div>\n    <div class=\"section hack\">\n      <div class=\"sec-head\"><span class=\"dot\"></span>🧠 เทคนิคจำ</div>\n      <div class=\"txt\">\"บังคับตัดก่อน ยกกำลังทีหลัง\"</div>\n    </div>\n    <div class=\"section examtip\">\n      <div class=\"sec-head\"><span class=\"dot\"></span>🎯 ข้อสอบชอบออก</div>\n      <p>โจทย์นับแบบมีเงื่อนไขมักให้ 'ต้องมี' และ 'ห้ามมี' พร้อมกัน คนพลาดเพราะรีบยกกำลังจากจำนวนรวม</p>\n    </div>\n    <div class=\"section checklist\">\n      <div class=\"sec-head\"><span class=\"dot\"></span>☑ Before You Submit</div>\n      <ul>\n      <li>ตัวไหนต้องมี</li>\n      <li>ตัวไหนห้ามมี</li>\n      </ul>\n    </div>\n    <div class=\"pagefoot\">SetTheoryRescueKit Rescue Kit · เปิดก่อนสอบ 10 นาที</div>\n  </div>"
    },
    {
      "id": "set-p3",
      "num": "PART 3",
      "name": "Power Sets",
      "th": "Power Sets",
      "cardCount": 4,
      "accent": "#2563eb",
      "gridHTML": "<div class=\"card\" data-accent=\"blue\">\n    <div class=\"card-head\">\n      <div class=\"eyebrow\">PART 3 · Power Sets · 🔵 Concept</div>\n      <div class=\"title\">เพาเวอร์เซต</div>\n    </div>\n    <div class=\"trigger-box\">\n      <div class=\"ic\">🎯</div>\n      <div class=\"txt\">เพาเวอร์เซตคือเซตของสับเซตทั้งหมด</div>\n    </div>\n    <div class=\"section when\">\n      <div class=\"sec-head\"><span class=\"dot\"></span>👀 เมื่อเจอโจทย์แบบนี้</div>\n      <ul>\n      <li>หา \\(P(A)\\) เมื่อ \\(A=\\{1,2\\}\\)</li>\n      <li>เช็กว่า \\(\\emptyset\\in P(A)\\) หรือไม่</li>\n      </ul>\n    </div>\n    <div class=\"section how\">\n      <div class=\"sec-head\"><span class=\"dot\"></span>✅ วิธีคิด</div>\n      <ol>\n      <li>เขียนสับเซตทุกตัวของ \\(A\\)</li>\n      <li>รวมเซตว่างด้วยเสมอ</li>\n      <li>จำว่าแต่ละสมาชิกของ \\(P(A)\\) เป็น 'สับเซต'</li>\n      </ol>\n    </div>\n    <div class=\"section mistake\">\n      <div class=\"sec-head\"><span class=\"dot\"></span>❌ จุดที่พลาดบ่อย</div>\n      <ul>\n      <li>คิดว่าสมาชิกของเพาเวอร์เซตต้องเป็นตัวเลข</li>\n      <li>ลืมใส่เซตว่าง</li>\n      </ul>\n    </div>\n    <div class=\"section hack\">\n      <div class=\"sec-head\"><span class=\"dot\"></span>🧠 เทคนิคจำ</div>\n      <div class=\"txt\">\"เพาเวอร์เซต = เซตของสับเซต\"</div>\n    </div>\n    <div class=\"section examtip\">\n      <div class=\"sec-head\"><span class=\"dot\"></span>🎯 ข้อสอบชอบออก</div>\n      <p>ข้อสอบชอบถามสมาชิกของ \\(P(A)\\) แบบสลับชั้น ถ้าไม่รู้ว่าข้างในต้องเป็นสับเซต จะโดนหลอกทันที</p>\n    </div>\n    <div class=\"section checklist\">\n      <div class=\"sec-head\"><span class=\"dot\"></span>☑ Before You Submit</div>\n      <ul>\n      <li>ข้างในเป็นสับเซตไหม</li>\n      <li>ครบทุกสับเซตแล้วหรือยัง</li>\n      </ul>\n    </div>\n    <div class=\"pagefoot\">SetTheoryRescueKit Rescue Kit · เปิดก่อนสอบ 10 นาที</div>\n  </div>\n\n\n  <div class=\"card\" data-accent=\"green\">\n    <div class=\"card-head\">\n      <div class=\"eyebrow\">PART 3 · Power Sets · 🟢 Formula</div>\n      <div class=\"title\">จำนวนสมาชิกเพาเวอร์เซต</div>\n    </div>\n    <div class=\"trigger-box\">\n      <div class=\"ic\">🎯</div>\n      <div class=\"txt\">เซตมี n ตัว เพาเวอร์เซตมีสองยกกำลัง n ตัว</div>\n    </div>\n    <div class=\"section when\">\n      <div class=\"sec-head\"><span class=\"dot\"></span>👀 เมื่อเจอโจทย์แบบนี้</div>\n      <ul>\n      <li>หา \\(n(P(A))\\) เมื่อ \\(n(A)=4\\)</li>\n      <li>หา \\(n(P(P(A)))\\) เมื่อ \\(n(A)=2\\)</li>\n      </ul>\n    </div>\n    <div class=\"section how\">\n      <div class=\"sec-head\"><span class=\"dot\"></span>✅ วิธีคิด</div>\n      <ol>\n      <li>หา \\(n(A)\\) ก่อน</li>\n      <li>ใช้ \\(n(P(A))=2^{n(A)}\\)</li>\n      <li>ซ้อนสองชั้นใช้ \\(2^{2^{n(A)}}\\)</li>\n      </ol>\n    </div>\n    <div class=\"section mistake\">\n      <div class=\"sec-head\"><span class=\"dot\"></span>❌ จุดที่พลาดบ่อย</div>\n      <ul>\n      <li>เอาเลขชั้นนอกมาคูณแทนยกกำลัง</li>\n      <li>ลืมว่าซ้อนเพาเวอร์เซตต้องยกกำลังซ้ำ</li>\n      </ul>\n    </div>\n    <div class=\"section hack\">\n      <div class=\"sec-head\"><span class=\"dot\"></span>🧠 เทคนิคจำ</div>\n      <div class=\"txt\">\"สับเซตยกกำลัง เพาเวอร์เซตยกซ้ำ\"</div>\n    </div>\n    <div class=\"section examtip\">\n      <div class=\"sec-head\"><span class=\"dot\"></span>🎯 ข้อสอบชอบออก</div>\n      <p>ข้อสอบมักออกเลขที่ดูใหญ่ แต่จริง ๆ ใช้สูตรตรง ๆ หากจำได้ว่าเพาเวอร์เซตโตแบบยกกำลัง</p>\n    </div>\n    <div class=\"section checklist\">\n      <div class=\"sec-head\"><span class=\"dot\"></span>☑ Before You Submit</div>\n      <ul>\n      <li>หา \\(n(A)\\) ถูกไหม</li>\n      <li>มีซ้อนกี่ชั้น</li>\n      </ul>\n    </div>\n    <div class=\"pagefoot\">SetTheoryRescueKit Rescue Kit · เปิดก่อนสอบ 10 นาที</div>\n  </div>\n\n\n  <div class=\"card\" data-accent=\"orange\">\n    <div class=\"card-head\">\n      <div class=\"eyebrow\">PART 3 · Power Sets · 🟠 Trigger</div>\n      <div class=\"title\">ทริกเพาเวอร์เซต</div>\n    </div>\n    <div class=\"trigger-box\">\n      <div class=\"ic\">🎯</div>\n      <div class=\"txt\">\\(\\emptyset\\) อยู่ในเพาเวอร์เซตเสมอ และ \\(A\\) ก็อยู่ด้วย</div>\n    </div>\n    <div class=\"section when\">\n      <div class=\"sec-head\"><span class=\"dot\"></span>👀 เมื่อเจอโจทย์แบบนี้</div>\n      <ul>\n      <li>ตรวจว่า \\(\\emptyset\\in P(A)\\)</li>\n      <li>ตรวจว่า \\(A\\in P(A)\\)</li>\n      </ul>\n    </div>\n    <div class=\"section how\">\n      <div class=\"sec-head\"><span class=\"dot\"></span>✅ วิธีคิด</div>\n      <ol>\n      <li>จำว่า \\(P(A)\\) เก็บสับเซตทั้งหมด</li>\n      <li>เพราะ \\(\\emptyset\\) เป็นสับเซตของทุกเซต</li>\n      <li>เพราะ \\(A\\) เป็นสับเซตของตัวเอง</li>\n      </ol>\n    </div>\n    <div class=\"section mistake\">\n      <div class=\"sec-head\"><span class=\"dot\"></span>❌ จุดที่พลาดบ่อย</div>\n      <ul>\n      <li>สับสน \\(\\emptyset\\in A\\) กับ \\(\\emptyset\\in P(A)\\)</li>\n      <li>คิดว่า \\(A\\in P(A)\\) ไม่ได้</li>\n      </ul>\n    </div>\n    <div class=\"section hack\">\n      <div class=\"sec-head\"><span class=\"dot\"></span>🧠 เทคนิคจำ</div>\n      <div class=\"txt\">\"ศูนย์อยู่เสมอ ก้อนใหญ่ก็อยู่\"</div>\n    </div>\n    <div class=\"section examtip\">\n      <div class=\"sec-head\"><span class=\"dot\"></span>🎯 ข้อสอบชอบออก</div>\n      <p>ข้อสอบชอบใช้ความจริงพื้นฐานสองข้อนี้ไปต่อยอดเป็น \\(\\{A\\}\\subset P(A)\\) หรือ \\(\\emptyset\\subset P(A)\\)</p>\n    </div>\n    <div class=\"section checklist\">\n      <div class=\"sec-head\"><span class=\"dot\"></span>☑ Before You Submit</div>\n      <ul>\n      <li>จำกฎ \\(\\emptyset\\) ไว้ไหม</li>\n      <li>จำว่า \\(A\\) เป็นสับเซตของตัวเองไหม</li>\n      </ul>\n    </div>\n    <div class=\"pagefoot\">SetTheoryRescueKit Rescue Kit · เปิดก่อนสอบ 10 นาที</div>\n  </div>\n\n\n  <div class=\"card\" data-accent=\"purple\">\n    <div class=\"card-head\">\n      <div class=\"eyebrow\">PART 3 · Power Sets · 🟣 Exam Tip</div>\n      <div class=\"title\">ชั้นปีกกา</div>\n    </div>\n    <div class=\"trigger-box\">\n      <div class=\"ic\">🎯</div>\n      <div class=\"txt\">สมาชิกของเพาเวอร์เซตต้องเป็นสับเซต ไม่ใช่สมาชิกดิบ</div>\n    </div>\n    <div class=\"section when\">\n      <div class=\"sec-head\"><span class=\"dot\"></span>👀 เมื่อเจอโจทย์แบบนี้</div>\n      <ul>\n      <li>พิจารณา \\(\\{A\\}\\subset P(A)\\)</li>\n      <li>พิจารณา \\(\\emptyset\\subset P(A)\\)</li>\n      </ul>\n    </div>\n    <div class=\"section how\">\n      <div class=\"sec-head\"><span class=\"dot\"></span>✅ วิธีคิด</div>\n      <ol>\n      <li>ถ้าจะอยู่ใน \\(P(A)\\) ต้องเป็นสับเซตของ \\(A\\)</li>\n      <li>ถ้าจะเป็นสมาชิกของ \\(P(A)\\) ห้ามเป็นตัวเดี่ยวแบบไม่ใช่เซต</li>\n      <li>ดูชั้นปีกกาก่อนตอบ</li>\n      </ol>\n    </div>\n    <div class=\"section mistake\">\n      <div class=\"sec-head\"><span class=\"dot\"></span>❌ จุดที่พลาดบ่อย</div>\n      <ul>\n      <li>ตอบว่า \\(A\\in A\\) ทั้งที่โจทย์ถาม \\(A\\in P(A)\\)</li>\n      <li>คิดว่า \\(\\{A\\}\\) เป็นสมาชิกของ \\(A\\)</li>\n      </ul>\n    </div>\n    <div class=\"section hack\">\n      <div class=\"sec-head\"><span class=\"dot\"></span>🧠 เทคนิคจำ</div>\n      <div class=\"txt\">\"ในเพาเวอร์เซต ข้างในต้องเป็นเซต\"</div>\n    </div>\n    <div class=\"section examtip\">\n      <div class=\"sec-head\"><span class=\"dot\"></span>🎯 ข้อสอบชอบออก</div>\n      <p>โจทย์ระดับสอบแข่งขันชอบวัดว่าแยก \\(A\\), \\(\\{A\\}\\), \\(P(A)\\) ได้ไหม ถ้าดูปีกกาเป็น จะรอด</p>\n    </div>\n    <div class=\"section checklist\">\n      <div class=\"sec-head\"><span class=\"dot\"></span>☑ Before You Submit</div>\n      <ul>\n      <li>ข้างในเป็นเซตหรือไม่</li>\n      <li>ถามอยู่ใน \\(A\\) หรือ \\(P(A)\\)</li>\n      </ul>\n    </div>\n    <div class=\"pagefoot\">SetTheoryRescueKit Rescue Kit · เปิดก่อนสอบ 10 นาที</div>\n  </div>"
    },
    {
      "id": "set-p4",
      "num": "PART 4",
      "name": "Core Set Operations",
      "th": "Core Set Operations",
      "cardCount": 4,
      "accent": "#2563eb",
      "gridHTML": "<div class=\"card\" data-accent=\"blue\">\n    <div class=\"card-head\">\n      <div class=\"eyebrow\">PART 4 · Core Set Operations · 🔵 Concept</div>\n      <div class=\"title\">ยูเนียน</div>\n    </div>\n    <div class=\"trigger-box\">\n      <div class=\"ic\">🎯</div>\n      <div class=\"txt\">เอาทุกส่วนมารวมกัน</div>\n    </div>\n    <div class=\"section when\">\n      <div class=\"sec-head\"><span class=\"dot\"></span>👀 เมื่อเจอโจทย์แบบนี้</div>\n      <ul>\n      <li>หาค่า \\(A \\cup B\\)</li>\n      <li>โจทย์ถาม 'อยู่ในอย่างน้อยหนึ่งเซต'</li>\n      </ul>\n    </div>\n    <div class=\"section how\">\n      <div class=\"sec-head\"><span class=\"dot\"></span>✅ วิธีคิด</div>\n      <ol>\n      <li>รวมสมาชิกของทั้งสองเซต</li>\n      <li>ตัดสมาชิกซ้ำออก 1 ครั้ง</li>\n      <li>เขียนผลลัพธ์เป็นเซตเดียว</li>\n      </ol>\n    </div>\n    <div class=\"section mistake\">\n      <div class=\"sec-head\"><span class=\"dot\"></span>❌ จุดที่พลาดบ่อย</div>\n      <ul>\n      <li>นับสมาชิกซ้ำสองครั้ง</li>\n      <li>สับสนกับส่วนร่วม \\(A \\cap B\\)</li>\n      </ul>\n    </div>\n    <div class=\"section hack\">\n      <div class=\"sec-head\"><span class=\"dot\"></span>🧠 เทคนิคจำ</div>\n      <div class=\"txt\">\"เอาทั้งหมด\"</div>\n    </div>\n    <div class=\"section examtip\">\n      <div class=\"sec-head\"><span class=\"dot\"></span>🎯 ข้อสอบชอบออก</div>\n      <p>ข้อสอบชอบให้รายชื่อสมาชิกหรือแผนภาพเวนน์ แล้วถามเซตรวม ต้องอ่านว่า 'อย่างน้อยหนึ่ง' ไม่ใช่ 'ทุกเซต'</p>\n    </div>\n    <div class=\"section checklist\">\n      <div class=\"sec-head\"><span class=\"dot\"></span>☑ Before You Submit</div>\n      <ul>\n      <li>มีสมาชิกจากทั้งสองฝั่งครบไหม</li>\n      <li>ตัดตัวซ้ำแล้วหรือยัง</li>\n      </ul>\n    </div>\n    <div class=\"pagefoot\">SetTheoryRescueKit Rescue Kit · เปิดก่อนสอบ 10 นาที</div>\n  </div>\n\n\n  <div class=\"card\" data-accent=\"green\">\n    <div class=\"card-head\">\n      <div class=\"eyebrow\">PART 4 · Core Set Operations · 🔵 Concept</div>\n      <div class=\"title\">อินเตอร์เซกชัน</div>\n    </div>\n    <div class=\"trigger-box\">\n      <div class=\"ic\">🎯</div>\n      <div class=\"txt\">เอาเฉพาะที่ซ้อนกัน</div>\n    </div>\n    <div class=\"section when\">\n      <div class=\"sec-head\"><span class=\"dot\"></span>👀 เมื่อเจอโจทย์แบบนี้</div>\n      <ul>\n      <li>หาค่า \\(A \\cap B\\)</li>\n      <li>โจทย์ถาม 'อยู่ร่วมกัน' หรือ 'ทั้งคู่'</li>\n      </ul>\n    </div>\n    <div class=\"section how\">\n      <div class=\"sec-head\"><span class=\"dot\"></span>✅ วิธีคิด</div>\n      <ol>\n      <li>หาสมาชิกที่อยู่ในทุกเซตที่กำหนด</li>\n      <li>ตัดตัวที่ไม่ร่วมออก</li>\n      <li>ตอบเฉพาะส่วนทับซ้อน</li>\n      </ol>\n    </div>\n    <div class=\"section mistake\">\n      <div class=\"sec-head\"><span class=\"dot\"></span>❌ จุดที่พลาดบ่อย</div>\n      <ul>\n      <li>เอาสมาชิกที่อยู่แค่ฝั่งเดียว</li>\n      <li>ลืมตรวจทุกเงื่อนไข</li>\n      </ul>\n    </div>\n    <div class=\"section hack\">\n      <div class=\"sec-head\"><span class=\"dot\"></span>🧠 เทคนิคจำ</div>\n      <div class=\"txt\">\"ร่วมเท่านั้น\"</div>\n    </div>\n    <div class=\"section examtip\">\n      <div class=\"sec-head\"><span class=\"dot\"></span>🎯 ข้อสอบชอบออก</div>\n      <p>ข้อสอบชอบหลอกด้วยคำว่า 'และ' ให้คิดเป็นส่วนตัดกันเสมอ โดยเฉพาะโจทย์ข้อความถูก-ผิด</p>\n    </div>\n    <div class=\"section checklist\">\n      <div class=\"sec-head\"><span class=\"dot\"></span>☑ Before You Submit</div>\n      <ul>\n      <li>อยู่ครบทุกเงื่อนไขไหม</li>\n      <li>มีตัวที่อยู่แค่ฝั่งเดียวหลุดมาหรือไม่</li>\n      </ul>\n    </div>\n    <div class=\"pagefoot\">SetTheoryRescueKit Rescue Kit · เปิดก่อนสอบ 10 นาที</div>\n  </div>\n\n\n  <div class=\"card\" data-accent=\"orange\">\n    <div class=\"card-head\">\n      <div class=\"eyebrow\">PART 4 · Core Set Operations · 🔵 Concept</div>\n      <div class=\"title\">คอมพลีเมนต์</div>\n    </div>\n    <div class=\"trigger-box\">\n      <div class=\"ic\">🎯</div>\n      <div class=\"txt\">ไม่เอาเซตเดิม เอาที่เหลือในเอกภพ</div>\n    </div>\n    <div class=\"section when\">\n      <div class=\"sec-head\"><span class=\"dot\"></span>👀 เมื่อเจอโจทย์แบบนี้</div>\n      <ul>\n      <li>หาค่า \\(A'\\)</li>\n      <li>โจทย์ถาม 'ไม่อยู่ใน A'</li>\n      </ul>\n    </div>\n    <div class=\"section how\">\n      <div class=\"sec-head\"><span class=\"dot\"></span>✅ วิธีคิด</div>\n      <ol>\n      <li>ดูเอกภพสัมพัทธ์ \\(U\\) ก่อน</li>\n      <li>ตัดสมาชิกที่อยู่ใน \\(A\\) ออก</li>\n      <li>เก็บสมาชิกที่เหลือทั้งหมด</li>\n      </ol>\n    </div>\n    <div class=\"section mistake\">\n      <div class=\"sec-head\"><span class=\"dot\"></span>❌ จุดที่พลาดบ่อย</div>\n      <ul>\n      <li>ลืมระบุเอกภพ \\(U\\)</li>\n      <li>คิดว่า 'ไม่อยู่ใน A' เท่ากับศูนย์</li>\n      </ul>\n    </div>\n    <div class=\"section hack\">\n      <div class=\"sec-head\"><span class=\"dot\"></span>🧠 เทคนิคจำ</div>\n      <div class=\"txt\">\"ใน U ที่ไม่ใช่ A\"</div>\n    </div>\n    <div class=\"section examtip\">\n      <div class=\"sec-head\"><span class=\"dot\"></span>🎯 ข้อสอบชอบออก</div>\n      <p>ข้อสอบชอบให้ \\(U\\) เปลี่ยนไปตามโจทย์ ถ้าไม่ดู \\(U\\) จะตอบผิดทั้งข้อ</p>\n    </div>\n    <div class=\"section checklist\">\n      <div class=\"sec-head\"><span class=\"dot\"></span>☑ Before You Submit</div>\n      <ul>\n      <li>กำหนดเอกภพแล้วหรือยัง</li>\n      <li>ตัดสมาชิกของ A ออกครบไหม</li>\n      </ul>\n    </div>\n    <div class=\"pagefoot\">SetTheoryRescueKit Rescue Kit · เปิดก่อนสอบ 10 นาที</div>\n  </div>\n\n\n  <div class=\"card\" data-accent=\"purple\">\n    <div class=\"card-head\">\n      <div class=\"eyebrow\">PART 4 · Core Set Operations · 🟢 Formula</div>\n      <div class=\"title\">ผลต่างเซต</div>\n    </div>\n    <div class=\"trigger-box\">\n      <div class=\"ic\">🎯</div>\n      <div class=\"txt\">เอาหน้า ไม่เอาหลัง</div>\n    </div>\n    <div class=\"section when\">\n      <div class=\"sec-head\"><span class=\"dot\"></span>👀 เมื่อเจอโจทย์แบบนี้</div>\n      <ul>\n      <li>หาค่า \\(A - B\\)</li>\n      <li>โจทย์ถาม 'อยู่ใน A แต่ไม่อยู่ใน B'</li>\n      </ul>\n    </div>\n    <div class=\"section how\">\n      <div class=\"sec-head\"><span class=\"dot\"></span>✅ วิธีคิด</div>\n      <ol>\n      <li>เริ่มจากสมาชิกของ \\(A\\)</li>\n      <li>ตัดตัวที่อยู่ใน \\(B\\) ออก</li>\n      <li>เขียนเฉพาะที่เหลือ</li>\n      </ol>\n    </div>\n    <div class=\"section mistake\">\n      <div class=\"sec-head\"><span class=\"dot\"></span>❌ จุดที่พลาดบ่อย</div>\n      <ul>\n      <li>สลับกับ \\(B - A\\)</li>\n      <li>คิดว่าเหมือน \\(A \\cap B\\)</li>\n      </ul>\n    </div>\n    <div class=\"section hack\">\n      <div class=\"sec-head\"><span class=\"dot\"></span>🧠 เทคนิคจำ</div>\n      <div class=\"txt\">\"หน้าอยู่ หลังหาย\"</div>\n    </div>\n    <div class=\"section examtip\">\n      <div class=\"sec-head\"><span class=\"dot\"></span>🎯 ข้อสอบชอบออก</div>\n      <p>ข้อสอบนิยมให้ผลต่างแล้วแปลงเป็นอินเตอร์เซกชันกับคอมพลีเมนต์ เช่น \\(A - B = A \\cap B'\\)</p>\n    </div>\n    <div class=\"section checklist\">\n      <div class=\"sec-head\"><span class=\"dot\"></span>☑ Before You Submit</div>\n      <ul>\n      <li>เริ่มจากเซตซ้ายใช่ไหม</li>\n      <li>ตัดสมาชิกที่ซ้ำกับขวาออกหมดหรือยัง</li>\n      </ul>\n    </div>\n    <div class=\"pagefoot\">SetTheoryRescueKit Rescue Kit · เปิดก่อนสอบ 10 นาที</div>\n  </div>"
    },
    {
      "id": "set-p5",
      "num": "PART 5",
      "name": "Set Identities",
      "th": "Set Identities",
      "cardCount": 4,
      "accent": "#2563eb",
      "gridHTML": "<div class=\"card\" data-accent=\"blue\">\n    <div class=\"card-head\">\n      <div class=\"eyebrow\">PART 5 · Set Identities · 🟢 Formula</div>\n      <div class=\"title\">ผลต่างเท่ากับตัดกับคอมพลีเมนต์</div>\n    </div>\n    <div class=\"trigger-box\">\n      <div class=\"ic\">🎯</div>\n      <div class=\"txt\">ลบเซต แปลว่า ตัดกับส่วนที่ไม่ใช่</div>\n    </div>\n    <div class=\"section when\">\n      <div class=\"sec-head\"><span class=\"dot\"></span>👀 เมื่อเจอโจทย์แบบนี้</div>\n      <ul>\n      <li>ยุบรูป \\(A - B\\)</li>\n      <li>แปลงโจทย์หาผลต่างให้สั้นลง</li>\n      </ul>\n    </div>\n    <div class=\"section how\">\n      <div class=\"sec-head\"><span class=\"dot\"></span>✅ วิธีคิด</div>\n      <ol>\n      <li>เขียน \\(A - B\\) ใหม่เป็น \\(A \\cap B'\\)</li>\n      <li>ใช้กฎคอมพลีเมนต์ของเซตขวา</li>\n      <li>ยุบรูปต่อถ้าจำเป็น</li>\n      </ol>\n    </div>\n    <div class=\"section mistake\">\n      <div class=\"sec-head\"><span class=\"dot\"></span>❌ จุดที่พลาดบ่อย</div>\n      <ul>\n      <li>ลบแล้วคิดว่าเป็นการเอาออกเฉยๆ โดยไม่ใช้กฎ</li>\n      <li>ลืมใส่เครื่องหมายคอมพลีเมนต์ \\(')</li>\n      </ul>\n    </div>\n    <div class=\"section hack\">\n      <div class=\"sec-head\"><span class=\"dot\"></span>🧠 เทคนิคจำ</div>\n      <div class=\"txt\">\"ลบ = ตัดกับไม่ใช่\"</div>\n    </div>\n    <div class=\"section examtip\">\n      <div class=\"sec-head\"><span class=\"dot\"></span>🎯 ข้อสอบชอบออก</div>\n      <p>นี่คือกฎแปลงรูปที่ออกบ่อยที่สุดในเซต ถ้าทำข้อนับหรือแรเงา ต้องแปลงกฎนี้ให้ไว</p>\n    </div>\n    <div class=\"section checklist\">\n      <div class=\"sec-head\"><span class=\"dot\"></span>☑ Before You Submit</div>\n      <ul>\n      <li>แปลงเป็น \\(A \\cap B'\\) แล้วหรือยัง</li>\n      <li>ใช้เอกภพถูกตัวหรือไม่</li>\n      </ul>\n    </div>\n    <div class=\"pagefoot\">SetTheoryRescueKit Rescue Kit · เปิดก่อนสอบ 10 นาที</div>\n  </div>\n\n\n  <div class=\"card\" data-accent=\"green\">\n    <div class=\"card-head\">\n      <div class=\"eyebrow\">PART 5 · Set Identities · 🟢 Formula</div>\n      <div class=\"title\">กฎของเดอมอร์แกน</div>\n    </div>\n    <div class=\"trigger-box\">\n      <div class=\"ic\">🎯</div>\n      <div class=\"txt\">กลับเครื่องหมาย แล้วสลับเป็นคู่</div>\n    </div>\n    <div class=\"section when\">\n      <div class=\"sec-head\"><span class=\"dot\"></span>👀 เมื่อเจอโจทย์แบบนี้</div>\n      <ul>\n      <li>หาค่า \\((A \\cup B)'\\)</li>\n      <li>หาค่า \\((A \\cap B)'\\)</li>\n      </ul>\n    </div>\n    <div class=\"section how\">\n      <div class=\"sec-head\"><span class=\"dot\"></span>✅ วิธีคิด</div>\n      <ol>\n      <li>คอมพลีเมนต์วงเล็บก่อน</li>\n      <li>สลับ \\(\\cup\\) เป็น \\(\\cap\\) หรือ \\(\\cap\\) เป็น \\(\\cup\\)</li>\n      <li>เติมเครื่องหมาย \\(') ให้ทุกตัว</li>\n      </ol>\n    </div>\n    <div class=\"section mistake\">\n      <div class=\"sec-head\"><span class=\"dot\"></span>❌ จุดที่พลาดบ่อย</div>\n      <ul>\n      <li>เติมคอมพลีเมนต์แค่ข้างเดียว</li>\n      <li>ลืมสลับยูเนียนกับอินเตอร์เซกชัน</li>\n      </ul>\n    </div>\n    <div class=\"section hack\">\n      <div class=\"sec-head\"><span class=\"dot\"></span>🧠 เทคนิคจำ</div>\n      <div class=\"txt\">\"กลับเครื่องหมาย สลับคู่\"</div>\n    </div>\n    <div class=\"section examtip\">\n      <div class=\"sec-head\"><span class=\"dot\"></span>🎯 ข้อสอบชอบออก</div>\n      <p>ข้อสอบชอบถามการแรเงาและยุบรูปพร้อมกัน ถ้าจำเดอมอร์แกนได้จะเร็วมาก</p>\n    </div>\n    <div class=\"section checklist\">\n      <div class=\"sec-head\"><span class=\"dot\"></span>☑ Before You Submit</div>\n      <ul>\n      <li>กลับทั้งก้อนแล้วหรือยัง</li>\n      <li>สลับสัญลักษณ์ครบไหม</li>\n      </ul>\n    </div>\n    <div class=\"pagefoot\">SetTheoryRescueKit Rescue Kit · เปิดก่อนสอบ 10 นาที</div>\n  </div>\n\n\n  <div class=\"card\" data-accent=\"orange\">\n    <div class=\"card-head\">\n      <div class=\"eyebrow\">PART 5 · Set Identities · 🟢 Formula</div>\n      <div class=\"title\">แจกแจง</div>\n    </div>\n    <div class=\"trigger-box\">\n      <div class=\"ic\">🎯</div>\n      <div class=\"txt\">กระจายเหมือนคูณพจน์</div>\n    </div>\n    <div class=\"section when\">\n      <div class=\"sec-head\"><span class=\"dot\"></span>👀 เมื่อเจอโจทย์แบบนี้</div>\n      <ul>\n      <li>ยุบรูป \\(A \\cap (B \\cup C)\\)</li>\n      <li>ยุบรูป \\(A \\cup (B \\cap C)\\)</li>\n      </ul>\n    </div>\n    <div class=\"section how\">\n      <div class=\"sec-head\"><span class=\"dot\"></span>✅ วิธีคิด</div>\n      <ol>\n      <li>ดูตัวที่อยู่นอกวงเล็บ</li>\n      <li>กระจายเข้าไปทีละตัว</li>\n      <li>รวมคำตอบตามกฎเซต</li>\n      </ol>\n    </div>\n    <div class=\"section mistake\">\n      <div class=\"sec-head\"><span class=\"dot\"></span>❌ จุดที่พลาดบ่อย</div>\n      <ul>\n      <li>กระจายผิดฝั่ง</li>\n      <li>ลืมวงเล็บทำให้รูปเปลี่ยน</li>\n      </ul>\n    </div>\n    <div class=\"section hack\">\n      <div class=\"sec-head\"><span class=\"dot\"></span>🧠 เทคนิคจำ</div>\n      <div class=\"txt\">\"นอกแจกเข้าใน\"</div>\n    </div>\n    <div class=\"section examtip\">\n      <div class=\"sec-head\"><span class=\"dot\"></span>🎯 ข้อสอบชอบออก</div>\n      <p>โจทย์ยุบรูปมักซ่อนการแจกแจงไว้ ถ้ามองเป็นพีชคณิตของเซตจะจับทางได้เร็ว</p>\n    </div>\n    <div class=\"section checklist\">\n      <div class=\"sec-head\"><span class=\"dot\"></span>☑ Before You Submit</div>\n      <ul>\n      <li>ตัวนอกวงเล็บคืออะไร</li>\n      <li>กระจายครบทุกพจน์ไหม</li>\n      </ul>\n    </div>\n    <div class=\"pagefoot\">SetTheoryRescueKit Rescue Kit · เปิดก่อนสอบ 10 นาที</div>\n  </div>\n\n\n  <div class=\"card\" data-accent=\"purple\">\n    <div class=\"card-head\">\n      <div class=\"eyebrow\">PART 5 · Set Identities · 🟢 Formula</div>\n      <div class=\"title\">ดูดซับ</div>\n    </div>\n    <div class=\"trigger-box\">\n      <div class=\"ic\">🎯</div>\n      <div class=\"txt\">มี A ซ้ำ ซัดทิ้งส่วนเกิน</div>\n    </div>\n    <div class=\"section when\">\n      <div class=\"sec-head\"><span class=\"dot\"></span>👀 เมื่อเจอโจทย์แบบนี้</div>\n      <ul>\n      <li>ยุบรูป \\(A \\cup (A \\cap B)\\)</li>\n      <li>ยุบรูป \\(A \\cap (A \\cup B)\\)</li>\n      </ul>\n    </div>\n    <div class=\"section how\">\n      <div class=\"sec-head\"><span class=\"dot\"></span>✅ วิธีคิด</div>\n      <ol>\n      <li>มองหาตัวซ้ำหลักคือ \\(A\\)</li>\n      <li>ตัดส่วนที่ซ้อนเกินออก</li>\n      <li>เหลือเซตหลักตัวเดิม</li>\n      </ol>\n    </div>\n    <div class=\"section mistake\">\n      <div class=\"sec-head\"><span class=\"dot\"></span>❌ จุดที่พลาดบ่อย</div>\n      <ul>\n      <li>พยายามยุบทั้งที่ยังไม่เห็นตัวซ้ำ</li>\n      <li>สับสนกับการแจกแจง</li>\n      </ul>\n    </div>\n    <div class=\"section hack\">\n      <div class=\"sec-head\"><span class=\"dot\"></span>🧠 เทคนิคจำ</div>\n      <div class=\"txt\">\"ซ้ำตัดทิ้ง\"</div>\n    </div>\n    <div class=\"section examtip\">\n      <div class=\"sec-head\"><span class=\"dot\"></span>🎯 ข้อสอบชอบออก</div>\n      <p>ออกบ่อยในข้อพิสูจน์สมบัติเซตและข้อยุบรูปสั้นๆ ถ้าเห็นรูปซ้ำให้ลองดูดซับก่อนเสมอ</p>\n    </div>\n    <div class=\"section checklist\">\n      <div class=\"sec-head\"><span class=\"dot\"></span>☑ Before You Submit</div>\n      <ul>\n      <li>มีตัวหลักซ้ำหรือไม่</li>\n      <li>ส่วนเกินหายไปแล้วไหม</li>\n      </ul>\n    </div>\n    <div class=\"pagefoot\">SetTheoryRescueKit Rescue Kit · เปิดก่อนสอบ 10 นาที</div>\n  </div>"
    },
    {
      "id": "set-p6",
      "num": "PART 6",
      "name": "Venn Diagram",
      "th": "Venn Diagram",
      "cardCount": 3,
      "accent": "#2563eb",
      "gridHTML": "<div class=\"card\" data-accent=\"blue\">\n    <div class=\"card-head\">\n      <div class=\"eyebrow\">PART 6 · Venn Diagram · 🔵 Concept</div>\n      <div class=\"title\">เวนน์ 2 เซต</div>\n    </div>\n    <div class=\"trigger-box\">\n      <div class=\"ic\">🎯</div>\n      <div class=\"txt\">สองเซต = สี่ช่อง</div>\n    </div>\n    <div class=\"section when\">\n      <div class=\"sec-head\"><span class=\"dot\"></span>👀 เมื่อเจอโจทย์แบบนี้</div>\n      <ul>\n      <li>แรเงา \\(A \\cup B\\)</li>\n      <li>แรเงา \\(A \\cap B\\)</li>\n      </ul>\n    </div>\n    <div class=\"section how\">\n      <div class=\"sec-head\"><span class=\"dot\"></span>✅ วิธีคิด</div>\n      <ol>\n      <li>แบ่งพื้นที่เป็น 4 ส่วน</li>\n      <li>เริ่มระบายจากส่วนที่ตรงเงื่อนไขก่อน</li>\n      <li>ตรวจส่วนที่ถูกตัดออกท้ายสุด</li>\n      </ol>\n    </div>\n    <div class=\"section mistake\">\n      <div class=\"sec-head\"><span class=\"dot\"></span>❌ จุดที่พลาดบ่อย</div>\n      <ul>\n      <li>ระบายทั้งวงโดยไม่ดูเงื่อนไข</li>\n      <li>ลืมส่วนกลางของสองเซต</li>\n      </ul>\n    </div>\n    <div class=\"section hack\">\n      <div class=\"sec-head\"><span class=\"dot\"></span>🧠 เทคนิคจำ</div>\n      <div class=\"txt\">\"สองเซต สี่ช่อง\"</div>\n    </div>\n    <div class=\"section examtip\">\n      <div class=\"sec-head\"><span class=\"dot\"></span>🎯 ข้อสอบชอบออก</div>\n      <p>ข้อสอบเวนน์ 2 เซตมักออกการแรเงาและนับจำนวนในแต่ละส่วน ต้องเริ่มจากแบ่ง 4 ช่องก่อน</p>\n    </div>\n    <div class=\"section checklist\">\n      <div class=\"sec-head\"><span class=\"dot\"></span>☑ Before You Submit</div>\n      <ul>\n      <li>แบ่งครบ 4 ส่วนแล้วหรือยัง</li>\n      <li>ส่วนกลางถูกระบายถูกไหม</li>\n      </ul>\n    </div>\n    <div class=\"pagefoot\">SetTheoryRescueKit Rescue Kit · เปิดก่อนสอบ 10 นาที</div>\n  </div>\n\n\n  <div class=\"card\" data-accent=\"green\">\n    <div class=\"card-head\">\n      <div class=\"eyebrow\">PART 6 · Venn Diagram · 🔵 Concept</div>\n      <div class=\"title\">เวนน์ 3 เซต</div>\n    </div>\n    <div class=\"trigger-box\">\n      <div class=\"ic\">🎯</div>\n      <div class=\"txt\">สามเซต = แปดส่วน</div>\n    </div>\n    <div class=\"section when\">\n      <div class=\"sec-head\"><span class=\"dot\"></span>👀 เมื่อเจอโจทย์แบบนี้</div>\n      <ul>\n      <li>แรเงา \\(A \\cap B \\cap C\\)</li>\n      <li>แรเงา \\((A \\cup B)'\\)</li>\n      </ul>\n    </div>\n    <div class=\"section how\">\n      <div class=\"sec-head\"><span class=\"dot\"></span>✅ วิธีคิด</div>\n      <ol>\n      <li>แบ่งพื้นที่เป็น 8 ส่วน</li>\n      <li>เติมส่วนกลางสุดก่อน</li>\n      <li>ไล่ออกไปด้านนอกทีละชั้น</li>\n      </ol>\n    </div>\n    <div class=\"section mistake\">\n      <div class=\"sec-head\"><span class=\"dot\"></span>❌ จุดที่พลาดบ่อย</div>\n      <ul>\n      <li>เริ่มเติมจากขอบนอกก่อน</li>\n      <li>ลืมส่วนทับซ้อนสามวง</li>\n      </ul>\n    </div>\n    <div class=\"section hack\">\n      <div class=\"sec-head\"><span class=\"dot\"></span>🧠 เทคนิคจำ</div>\n      <div class=\"txt\">\"สามเซต แปดส่วน\"</div>\n    </div>\n    <div class=\"section examtip\">\n      <div class=\"sec-head\"><span class=\"dot\"></span>🎯 ข้อสอบชอบออก</div>\n      <p>ถ้าเป็น 3 เซต อย่ากระโดดลงสีทันที ต้องนึกเป็น 8 ส่วนก่อน ข้อสอบชอบหลอกด้วยส่วนกลาง</p>\n    </div>\n    <div class=\"section checklist\">\n      <div class=\"sec-head\"><span class=\"dot\"></span>☑ Before You Submit</div>\n      <ul>\n      <li>มี 8 ส่วนหรือยัง</li>\n      <li>ส่วนกลางสุดเติมก่อนหรือเปล่า</li>\n      </ul>\n    </div>\n    <div class=\"pagefoot\">SetTheoryRescueKit Rescue Kit · เปิดก่อนสอบ 10 นาที</div>\n  </div>\n\n\n  <div class=\"card\" data-accent=\"orange\">\n    <div class=\"card-head\">\n      <div class=\"eyebrow\">PART 6 · Venn Diagram · 🟠 Trigger</div>\n      <div class=\"title\">แรเงาแล้วเทียบ</div>\n    </div>\n    <div class=\"trigger-box\">\n      <div class=\"ic\">🎯</div>\n      <div class=\"txt\">แรเงาก่อน เทียบทีหลัง</div>\n    </div>\n    <div class=\"section when\">\n      <div class=\"sec-head\"><span class=\"dot\"></span>👀 เมื่อเจอโจทย์แบบนี้</div>\n      <ul>\n      <li>เช็กว่าเซตสองรูปเท่ากันหรือไม่</li>\n      <li>พิสูจน์ว่า \\((A \\cap B) - C\\) ตรงกับแบบไหน</li>\n      </ul>\n    </div>\n    <div class=\"section how\">\n      <div class=\"sec-head\"><span class=\"dot\"></span>✅ วิธีคิด</div>\n      <ol>\n      <li>แรเงารูปแรก</li>\n      <li>แรเงารูปที่สอง</li>\n      <li>เทียบพื้นที่ที่ได้ว่าตรงกันหรือไม่</li>\n      </ol>\n    </div>\n    <div class=\"section mistake\">\n      <div class=\"sec-head\"><span class=\"dot\"></span>❌ จุดที่พลาดบ่อย</div>\n      <ul>\n      <li>ใช้สูตรจำอย่างเดียวโดยไม่แรเงา</li>\n      <li>เทียบจากชื่อสัญลักษณ์แทนพื้นที่จริง</li>\n      </ul>\n    </div>\n    <div class=\"section hack\">\n      <div class=\"sec-head\"><span class=\"dot\"></span>🧠 เทคนิคจำ</div>\n      <div class=\"txt\">\"ระบายก่อน ค่อยเทียบ\"</div>\n    </div>\n    <div class=\"section examtip\">\n      <div class=\"sec-head\"><span class=\"dot\"></span>🎯 ข้อสอบชอบออก</div>\n      <p>โจทย์ความเท่ากันของเซตมักซ่อนในรูปแผนภาพ ถ้าแรเงาเก่งจะตอบได้เร็วและแม่นกว่าเดาสูตร</p>\n    </div>\n    <div class=\"section checklist\">\n      <div class=\"sec-head\"><span class=\"dot\"></span>☑ Before You Submit</div>\n      <ul>\n      <li>แรเงาตรงตามเงื่อนไขไหม</li>\n      <li>สองรูปให้พื้นที่เดียวกันหรือไม่</li>\n      </ul>\n    </div>\n    <div class=\"pagefoot\">SetTheoryRescueKit Rescue Kit · เปิดก่อนสอบ 10 นาที</div>\n  </div>"
    },
    {
      "id": "set-p7",
      "num": "PART 7",
      "name": "Cardinality2Sets",
      "th": "Cardinality2Sets",
      "cardCount": 2,
      "accent": "#2563eb",
      "gridHTML": "<div class=\"card\" data-accent=\"blue\">\n    <div class=\"card-head\">\n      <div class=\"eyebrow\">PART 7 · Cardinality2Sets · 🟢 Formula</div>\n      <div class=\"title\">จำนวนสมาชิกสองเซต</div>\n    </div>\n    <div class=\"trigger-box\">\n      <div class=\"ic\">🎯</div>\n      <div class=\"txt\">รวมสองเซต ลบส่วนซ้ำก่อน</div>\n    </div>\n    <div class=\"section when\">\n      <div class=\"sec-head\"><span class=\"dot\"></span>👀 เมื่อเจอโจทย์แบบนี้</div>\n      <ul>\n      <li>หา \\(n(A \\cup B)\\) จาก \\(n(A)\\), \\(n(B)\\), \\(n(A \\cap B)\\)</li>\n      <li>โจทย์ให้ \\(n(A-B)\\), \\(n(B-A)\\), \\(n(A \\cap B)\\)</li>\n      </ul>\n    </div>\n    <div class=\"section how\">\n      <div class=\"sec-head\"><span class=\"dot\"></span>✅ วิธีคิด</div>\n      <ol>\n      <li>ใช้ \\(n(A \\cup B)=n(A)+n(B)-n(A \\cap B)\\)</li>\n      <li>ถ้าให้ผลต่าง ใช้ \\(n(A \\cup B)=n(A-B)+n(B-A)+n(A \\cap B)\\)</li>\n      <li>ถ้าไม่มีสูตร วาดเวนน์แล้วเติมจากกลางออกนอก</li>\n      </ol>\n    </div>\n    <div class=\"section mistake\">\n      <div class=\"sec-head\"><span class=\"dot\"></span>❌ จุดที่พลาดบ่อย</div>\n      <ul>\n      <li>บวกส่วนซ้ำสองครั้ง</li>\n      <li>ลืมว่า \\(A-B\\) คือเฉพาะที่อยู่ใน A แต่ไม่อยู่ใน B</li>\n      </ul>\n    </div>\n    <div class=\"section hack\">\n      <div class=\"sec-head\"><span class=\"dot\"></span>🧠 เทคนิคจำ</div>\n      <div class=\"txt\">\"รวมก่อน ลบซ้ำทีเดียว\"</div>\n    </div>\n    <div class=\"section examtip\">\n      <div class=\"sec-head\"><span class=\"dot\"></span>🎯 ข้อสอบชอบออก</div>\n      <p>ข้อสอบชอบให้ข้อมูลกระจัดกระจาย แล้วให้รวมจำนวนสมาชิกของยูเนียนหรืออินเตอร์เซกชัน เด็กที่วาดเวนน์ก่อนมักทำได้เร็วกว่าใช้สูตรลอยๆ</p>\n    </div>\n    <div class=\"section checklist\">\n      <div class=\"sec-head\"><span class=\"dot\"></span>☑ Before You Submit</div>\n      <ul>\n      <li>เช็กว่ามีส่วนซ้ำไหม</li>\n      <li>เช็กว่าควรใช้เวนน์หรือสูตร</li>\n      </ul>\n    </div>\n    <div class=\"pagefoot\">SetTheoryRescueKit Rescue Kit · เปิดก่อนสอบ 10 นาที</div>\n  </div>\n\n\n  <div class=\"card\" data-accent=\"green\">\n    <div class=\"card-head\">\n      <div class=\"eyebrow\">PART 7 · Cardinality2Sets · 🟠 Trigger</div>\n      <div class=\"title\">วาดเวนน์เติมจากกลาง</div>\n    </div>\n    <div class=\"trigger-box\">\n      <div class=\"ic\">🎯</div>\n      <div class=\"txt\">กลางก่อน นอกทีหลัง</div>\n    </div>\n    <div class=\"section when\">\n      <div class=\"sec-head\"><span class=\"dot\"></span>👀 เมื่อเจอโจทย์แบบนี้</div>\n      <ul>\n      <li>โจทย์ให้ \\(n(A \\cap B)\\) และจำนวนที่เหลือ</li>\n      <li>โจทย์ถามหาจำนวนสมาชิกแต่ละส่วนในแผนภาพ</li>\n      </ul>\n    </div>\n    <div class=\"section how\">\n      <div class=\"sec-head\"><span class=\"dot\"></span>✅ วิธีคิด</div>\n      <ol>\n      <li>เริ่มใส่ค่าตรง \\(A \\cap B\\)</li>\n      <li>ค่อยใส่ \\(A-B\\) และ \\(B-A\\)</li>\n      <li>สุดท้ายรวมทุกช่องเพื่อหา \\(n(A \\cup B)\\)</li>\n      </ol>\n    </div>\n    <div class=\"section mistake\">\n      <div class=\"sec-head\"><span class=\"dot\"></span>❌ จุดที่พลาดบ่อย</div>\n      <ul>\n      <li>เริ่มใส่จากกรอบนอกก่อนแล้วชนกัน</li>\n      <li>ลืมแยกส่วนที่ซ้อนกับส่วนที่ไม่ซ้อน</li>\n      </ul>\n    </div>\n    <div class=\"section hack\">\n      <div class=\"sec-head\"><span class=\"dot\"></span>🧠 เทคนิคจำ</div>\n      <div class=\"txt\">\"กลางมาก่อน รอบนอกตาม\"</div>\n    </div>\n    <div class=\"section examtip\">\n      <div class=\"sec-head\"><span class=\"dot\"></span>🎯 ข้อสอบชอบออก</div>\n      <p>ข้อสอบมักซ่อนค่ากลางไว้ แล้วถามค่ารวม ถ้าลงช่องกลางผิด ทุกช่องจะผิดตาม</p>\n    </div>\n    <div class=\"section checklist\">\n      <div class=\"sec-head\"><span class=\"dot\"></span>☑ Before You Submit</div>\n      <ul>\n      <li>ลงช่องกลางครบหรือยัง</li>\n      <li>รวมทุกช่องถูกหรือยัง</li>\n      </ul>\n    </div>\n    <div class=\"pagefoot\">SetTheoryRescueKit Rescue Kit · เปิดก่อนสอบ 10 นาที</div>\n  </div>"
    },
    {
      "id": "set-p8",
      "num": "PART 8",
      "name": "Cardinality3Sets",
      "th": "Cardinality3Sets",
      "cardCount": 3,
      "accent": "#2563eb",
      "gridHTML": "<div class=\"card\" data-accent=\"blue\">\n    <div class=\"card-head\">\n      <div class=\"eyebrow\">PART 8 · Cardinality3Sets · 🟢 Formula</div>\n      <div class=\"title\">สูตรสามเซต</div>\n    </div>\n    <div class=\"trigger-box\">\n      <div class=\"ic\">🎯</div>\n      <div class=\"txt\">บวกสาม ลบคู่ เติมกลาง</div>\n    </div>\n    <div class=\"section when\">\n      <div class=\"sec-head\"><span class=\"dot\"></span>👀 เมื่อเจอโจทย์แบบนี้</div>\n      <ul>\n      <li>หา \\(n(A \\cup B \\cup C)\\)</li>\n      <li>โจทย์ให้จำนวนตัดกันเป็นคู่และสามเซต</li>\n      </ul>\n    </div>\n    <div class=\"section how\">\n      <div class=\"sec-head\"><span class=\"dot\"></span>✅ วิธีคิด</div>\n      <ol>\n      <li>บวก \\(n(A), n(B), n(C)\\)</li>\n      <li>ลบ \\(n(A \\cap B), n(B \\cap C), n(C \\cap A)\\)</li>\n      <li>บวกกลับ \\(n(A \\cap B \\cap C)\\)</li>\n      </ol>\n    </div>\n    <div class=\"section mistake\">\n      <div class=\"sec-head\"><span class=\"dot\"></span>❌ จุดที่พลาดบ่อย</div>\n      <ul>\n      <li>ลืมบวกส่วนตัดกันสามเซตกลับเข้าไป</li>\n      <li>สับสนว่าเลขช่องคู่ต้องลบ หรือบวก</li>\n      </ul>\n    </div>\n    <div class=\"section hack\">\n      <div class=\"sec-head\"><span class=\"dot\"></span>🧠 เทคนิคจำ</div>\n      <div class=\"txt\">\"บวก ลบ ลบ ลบ บวกกลาง\"</div>\n    </div>\n    <div class=\"section examtip\">\n      <div class=\"sec-head\"><span class=\"dot\"></span>🎯 ข้อสอบชอบออก</div>\n      <p>โจทย์สามเซตชอบใช้ตัวเลขหลายชั้น เด็กที่จำลำดับบวก-ลบได้จะไม่หลงในสูตรยาว</p>\n    </div>\n    <div class=\"section checklist\">\n      <div class=\"sec-head\"><span class=\"dot\"></span>☑ Before You Submit</div>\n      <ul>\n      <li>ลบส่วนคู่ครบหรือยัง</li>\n      <li>บวกส่วนกลางกลับแล้วหรือยัง</li>\n      </ul>\n    </div>\n    <div class=\"pagefoot\">SetTheoryRescueKit Rescue Kit · เปิดก่อนสอบ 10 นาที</div>\n  </div>\n\n\n  <div class=\"card\" data-accent=\"green\">\n    <div class=\"card-head\">\n      <div class=\"eyebrow\">PART 8 · Cardinality3Sets · 🔵 Concept</div>\n      <div class=\"title\">แปดช่องไม่โดนหลอก</div>\n    </div>\n    <div class=\"trigger-box\">\n      <div class=\"ic\">🎯</div>\n      <div class=\"txt\">คำว่าเท่านั้น เปลี่ยนช่องที่นับ</div>\n    </div>\n    <div class=\"section when\">\n      <div class=\"sec-head\"><span class=\"dot\"></span>👀 เมื่อเจอโจทย์แบบนี้</div>\n      <ul>\n      <li>โจทย์ถามจำนวนที่ชอบอย่างน้อย 1 อย่าง</li>\n      <li>โจทย์ถามจำนวนที่ชอบเพียง 2 อย่างเท่านั้น</li>\n      </ul>\n    </div>\n    <div class=\"section how\">\n      <div class=\"sec-head\"><span class=\"dot\"></span>✅ วิธีคิด</div>\n      <ol>\n      <li>แยกพื้นที่เป็น 8 ช่องของแผนภาพเวนน์</li>\n      <li>อ่านคำว่า 'อย่างน้อย' คือรวมทุกช่องที่เข้าเงื่อนไข</li>\n      <li>อ่านคำว่า 'เท่านั้น' คือเอาเฉพาะช่องตรงเงื่อนไขจริง</li>\n      </ol>\n    </div>\n    <div class=\"section mistake\">\n      <div class=\"sec-head\"><span class=\"dot\"></span>❌ จุดที่พลาดบ่อย</div>\n      <ul>\n      <li>นับรวมช่องเกินเพราะไม่อ่านคำว่าเท่านั้น</li>\n      <li>ลืมว่าช่องนอกวงคือไม่อยู่ในเซตใดเลย</li>\n      </ul>\n    </div>\n    <div class=\"section hack\">\n      <div class=\"sec-head\"><span class=\"dot\"></span>🧠 เทคนิคจำ</div>\n      <div class=\"txt\">\"เท่านั้น = ตัดเกิน\"</div>\n    </div>\n    <div class=\"section examtip\">\n      <div class=\"sec-head\"><span class=\"dot\"></span>🎯 ข้อสอบชอบออก</div>\n      <p>ข้อสอบชอบหลอกด้วยถ้อยคำ เช่น 'อย่างน้อย 1' กับ 'เพียง 2 เท่านั้น' ต่างกันมาก ต้องแปลงเป็นช่องเวนน์ก่อนนับเสมอ</p>\n    </div>\n    <div class=\"section checklist\">\n      <div class=\"sec-head\"><span class=\"dot\"></span>☑ Before You Submit</div>\n      <ul>\n      <li>แปลงคำเป็นช่องแล้วหรือยัง</li>\n      <li>มีช่องนอกวงที่ต้องรวมไหม</li>\n      </ul>\n    </div>\n    <div class=\"pagefoot\">SetTheoryRescueKit Rescue Kit · เปิดก่อนสอบ 10 นาที</div>\n  </div>\n\n\n  <div class=\"card\" data-accent=\"orange\">\n    <div class=\"card-head\">\n      <div class=\"eyebrow\">PART 8 · Cardinality3Sets · 🟣 Exam Tip</div>\n      <div class=\"title\">กรอกเวนน์ให้ถูกลำดับ</div>\n    </div>\n    <div class=\"trigger-box\">\n      <div class=\"ic\">🎯</div>\n      <div class=\"txt\">กลางสุดก่อน เสมอ</div>\n    </div>\n    <div class=\"section when\">\n      <div class=\"sec-head\"><span class=\"dot\"></span>👀 เมื่อเจอโจทย์แบบนี้</div>\n      <ul>\n      <li>โจทย์ให้จำนวนแต่ละเซตและจุดตัดหลายชั้น</li>\n      <li>โจทย์ให้ 'มีอย่างน้อย 1 อย่าง'</li>\n      </ul>\n    </div>\n    <div class=\"section how\">\n      <div class=\"sec-head\"><span class=\"dot\"></span>✅ วิธีคิด</div>\n      <ol>\n      <li>ใส่ช่อง \\(A \\cap B \\cap C\\) ก่อน</li>\n      <li>ค่อยกระจายไปช่องตัดกันเป็นคู่</li>\n      <li>สุดท้ายเติมช่องเดี่ยวและช่องนอกวง</li>\n      </ol>\n    </div>\n    <div class=\"section mistake\">\n      <div class=\"sec-head\"><span class=\"dot\"></span>❌ จุดที่พลาดบ่อย</div>\n      <ul>\n      <li>เริ่มจากช่องเดี่ยวแล้วหักลบผิด</li>\n      <li>ใส่ช่องซ้ำซ้อนทับกัน</li>\n      </ul>\n    </div>\n    <div class=\"section hack\">\n      <div class=\"sec-head\"><span class=\"dot\"></span>🧠 เทคนิคจำ</div>\n      <div class=\"txt\">\"กลางก่อน ไม่หลงทาง\"</div>\n    </div>\n    <div class=\"section examtip\">\n      <div class=\"sec-head\"><span class=\"dot\"></span>🎯 ข้อสอบชอบออก</div>\n      <p>ถ้าใส่จากกลางออกนอก จะกันความผิดพลาดเรื่องซ้อนทับได้ดีที่สุด โดยเฉพาะข้อที่ให้ข้อมูลหลายบรรทัด</p>\n    </div>\n    <div class=\"section checklist\">\n      <div class=\"sec-head\"><span class=\"dot\"></span>☑ Before You Submit</div>\n      <ul>\n      <li>กลางสุดใส่แล้วหรือยัง</li>\n      <li>ช่องคู่และช่องเดี่ยวไม่ซ้ำกันใช่ไหม</li>\n      </ul>\n    </div>\n    <div class=\"pagefoot\">SetTheoryRescueKit Rescue Kit · เปิดก่อนสอบ 10 นาที</div>\n  </div>"
    },
    {
      "id": "set-p9",
      "num": "PART 9",
      "name": "SetOptimization",
      "th": "SetOptimization",
      "cardCount": 3,
      "accent": "#2563eb",
      "gridHTML": "<div class=\"card\" data-accent=\"blue\">\n    <div class=\"card-head\">\n      <div class=\"eyebrow\">PART 9 · SetOptimization · 🔵 Concept</div>\n      <div class=\"title\">หาอินเตอร์เซกชันมากสุด</div>\n    </div>\n    <div class=\"trigger-box\">\n      <div class=\"ic\">🎯</div>\n      <div class=\"txt\">ซ้อนให้มากที่สุด</div>\n    </div>\n    <div class=\"section when\">\n      <div class=\"sec-head\"><span class=\"dot\"></span>👀 เมื่อเจอโจทย์แบบนี้</div>\n      <ul>\n      <li>หาค่าสูงสุดของ \\(n(A \\cap B)\\)</li>\n      <li>โจทย์ให้ขอบเขตของเอกภพสัมพัทธ์</li>\n      </ul>\n    </div>\n    <div class=\"section how\">\n      <div class=\"sec-head\"><span class=\"dot\"></span>✅ วิธีคิด</div>\n      <ol>\n      <li>ดูว่าเซตไหนเล็กกว่า</li>\n      <li>ให้เซตเล็กซ้อนอยู่ในเซตใหญ่ทั้งหมด</li>\n      <li>ค่าสูงสุดของ \\(n(A \\cap B)\\) คือค่าของเซตที่เล็กกว่า</li>\n      </ol>\n    </div>\n    <div class=\"section mistake\">\n      <div class=\"sec-head\"><span class=\"dot\"></span>❌ จุดที่พลาดบ่อย</div>\n      <ul>\n      <li>ฝืนให้จุดตัดเกินเซตเล็ก</li>\n      <li>ลืมเช็กขอบเขตจาก \\(U\\)</li>\n      </ul>\n    </div>\n    <div class=\"section hack\">\n      <div class=\"sec-head\"><span class=\"dot\"></span>🧠 เทคนิคจำ</div>\n      <div class=\"txt\">\"เล็กซ้อนใหญ่ = จุดตัดมากสุด\"</div>\n    </div>\n    <div class=\"section examtip\">\n      <div class=\"sec-head\"><span class=\"dot\"></span>🎯 ข้อสอบชอบออก</div>\n      <p>ข้อสอบ optimization มักถามค่ามากสุดของจุดตัด ถ้าเห็นเงื่อนไขจำกัด ให้คิดว่าเอาอะไรไปซ้อนกับอะไรได้มากที่สุด</p>\n    </div>\n    <div class=\"section checklist\">\n      <div class=\"sec-head\"><span class=\"dot\"></span>☑ Before You Submit</div>\n      <ul>\n      <li>เซตเล็กคืออะไร</li>\n      <li>ซ้อนได้เต็มหรือยัง</li>\n      </ul>\n    </div>\n    <div class=\"pagefoot\">SetTheoryRescueKit Rescue Kit · เปิดก่อนสอบ 10 นาที</div>\n  </div>\n\n\n  <div class=\"card\" data-accent=\"green\">\n    <div class=\"card-head\">\n      <div class=\"eyebrow\">PART 9 · SetOptimization · 🟢 Formula</div>\n      <div class=\"title\">หายูเนียนมากสุดน้อยสุด</div>\n    </div>\n    <div class=\"trigger-box\">\n      <div class=\"ic\">🎯</div>\n      <div class=\"txt\">ยูเนียนใหญ่สุด เมื่อซ้อนน้อยสุด</div>\n    </div>\n    <div class=\"section when\">\n      <div class=\"sec-head\"><span class=\"dot\"></span>👀 เมื่อเจอโจทย์แบบนี้</div>\n      <ul>\n      <li>หาค่าสูงสุดของ \\(n(A \\cup B)\\)</li>\n      <li>หาค่าต่ำสุดของ \\(n(A \\cup B)\\) ภายใต้ \\(U\\)</li>\n      </ul>\n    </div>\n    <div class=\"section how\">\n      <div class=\"sec-head\"><span class=\"dot\"></span>✅ วิธีคิด</div>\n      <ol>\n      <li>ใช้ \\(n(A \\cup B)=n(A)+n(B)-n(A \\cap B)\\)</li>\n      <li>ถ้าอยากให้ยูเนียนมากสุด ให้ \\(A \\cap B\\) น้อยสุด</li>\n      <li>ถ้าอยากให้ยูเนียนน้อยสุด ให้ซ้อนกันมากสุด แต่ไม่เกินเซตเล็ก</li>\n      </ol>\n    </div>\n    <div class=\"section mistake\">\n      <div class=\"sec-head\"><span class=\"dot\"></span>❌ จุดที่พลาดบ่อย</div>\n      <ul>\n      <li>คิดว่ายูเนียนมากสุดต้องให้จุดตัดมากสุดเสมอ</li>\n      <li>ลืมว่าอยู่ภายใต้ขอบเขตของ \\(U\\)</li>\n      </ul>\n    </div>\n    <div class=\"section hack\">\n      <div class=\"sec-head\"><span class=\"dot\"></span>🧠 เทคนิคจำ</div>\n      <div class=\"txt\">\"ยูเนียนกว้าง จุดตัดแคบ\"</div>\n    </div>\n    <div class=\"section examtip\">\n      <div class=\"sec-head\"><span class=\"dot\"></span>🎯 ข้อสอบชอบออก</div>\n      <p>โจทย์หาค่าสูงสุดหรือต่ำสุดมักแฝงด้วยขอบเขตจากเอกภพ ต้องดูว่าค่าจริงติดเพดานหรือชนพื้นก่อน</p>\n    </div>\n    <div class=\"section checklist\">\n      <div class=\"sec-head\"><span class=\"dot\"></span>☑ Before You Submit</div>\n      <ul>\n      <li>ใช้สูตรยูเนียนถูกไหม</li>\n      <li>จุดตัดทำให้ค่าขึ้นหรือลง</li>\n      </ul>\n    </div>\n    <div class=\"pagefoot\">SetTheoryRescueKit Rescue Kit · เปิดก่อนสอบ 10 นาที</div>\n  </div>\n\n\n  <div class=\"card\" data-accent=\"orange\">\n    <div class=\"card-head\">\n      <div class=\"eyebrow\">PART 9 · SetOptimization · 🔵 Concept</div>\n      <div class=\"title\">จำเพดานกับพื้น</div>\n    </div>\n    <div class=\"trigger-box\">\n      <div class=\"ic\">🎯</div>\n      <div class=\"txt\">ติดเพดานก่อน ค่อยคิดสูตร</div>\n    </div>\n    <div class=\"section when\">\n      <div class=\"sec-head\"><span class=\"dot\"></span>👀 เมื่อเจอโจทย์แบบนี้</div>\n      <ul>\n      <li>โจทย์มีจำนวนสมาชิกใน \\(U\\) จำกัด</li>\n      <li>ต้องหาค่าที่เป็นไปได้จริง</li>\n      </ul>\n    </div>\n    <div class=\"section how\">\n      <div class=\"sec-head\"><span class=\"dot\"></span>✅ วิธีคิด</div>\n      <ol>\n      <li>เช็กเพดานว่าเซตใดเกิน \\(U\\) ได้ไหม</li>\n      <li>เช็กพื้นว่าค่าติดลบหรือไม่</li>\n      <li>สรุปคำตอบจากค่าที่ทำได้จริงเท่านั้น</li>\n      </ol>\n    </div>\n    <div class=\"section mistake\">\n      <div class=\"sec-head\"><span class=\"dot\"></span>❌ จุดที่พลาดบ่อย</div>\n      <ul>\n      <li>ตอบค่าตามสูตรโดยไม่เช็กความเป็นไปได้</li>\n      <li>ลืมว่าบางค่าต้องเป็นจำนวนเต็ม</li>\n      </ul>\n    </div>\n    <div class=\"section hack\">\n      <div class=\"sec-head\"><span class=\"dot\"></span>🧠 เทคนิคจำ</div>\n      <div class=\"txt\">\"เช็กเพดานก่อนตอบ\"</div>\n    </div>\n    <div class=\"section examtip\">\n      <div class=\"sec-head\"><span class=\"dot\"></span>🎯 ข้อสอบชอบออก</div>\n      <p>ข้อสอบบางข้อให้ค่าที่ดูเหมือนคำนวณได้ แต่จริงๆ เกินขอบเขตของเอกภพ ถ้าไม่เช็กจะเสียคะแนนง่าย</p>\n    </div>\n    <div class=\"section checklist\">\n      <div class=\"sec-head\"><span class=\"dot\"></span>☑ Before You Submit</div>\n      <ul>\n      <li>เกิน \\(U\\) ไหม</li>\n      <li>ได้จำนวนเต็มไหม</li>\n      </ul>\n    </div>\n    <div class=\"pagefoot\">SetTheoryRescueKit Rescue Kit · เปิดก่อนสอบ 10 นาที</div>\n  </div>"
    },
    {
      "id": "set-p10",
      "num": "PART 12",
      "name": "ExamRescue",
      "th": "ExamRescue",
      "cardCount": 1,
      "accent": "#2563eb",
      "gridHTML": "<div class=\"card\" data-accent=\"blue\">\n    <div class=\"card-head\">\n      <div class=\"eyebrow\">PART 12 · ExamRescue · 🟣 Exam Tip</div>\n      <div class=\"title\">รีวิวหนึ่งนาที</div>\n    </div>\n    <div class=\"trigger-box\">\n      <div class=\"ic\">🎯</div>\n      <div class=\"txt\">ท่องสั้นก่อนเข้าห้องสอบ ให้สมองเปิดไฟทันที</div>\n    </div>\n    <div class=\"section when\">\n      <div class=\"sec-head\"><span class=\"dot\"></span>👀 เมื่อเจอโจทย์แบบนี้</div>\n      <ul>\n      <li>ก่อนเริ่มทำข้อสอบ</li>\n      <li>ก่อนเช็กคำตอบรอบสุดท้าย</li>\n      </ul>\n    </div>\n    <div class=\"section how\">\n      <div class=\"sec-head\"><span class=\"dot\"></span>✅ วิธีคิด</div>\n      <ol>\n      <li>จำ \\(A \\cap B\\), \\(A \\cup B\\), \\(A - B\\)</li>\n      <li>จำ \\(A - B = A \\cap B'\\)</li>\n      <li>จำ \\(\\emptyset \\subset A\\)</li>\n      </ol>\n    </div>\n    <div class=\"section mistake\">\n      <div class=\"sec-head\"><span class=\"dot\"></span>❌ จุดที่พลาดบ่อย</div>\n      <ul>\n      <li>รีบลืมกฎพื้นฐาน</li>\n      <li>เริ่มทำโดยไม่อ่านคำถามเฉพาะ</li>\n      </ul>\n    </div>\n    <div class=\"section hack\">\n      <div class=\"sec-head\"><span class=\"dot\"></span>🧠 เทคนิคจำ</div>\n      <div class=\"txt\">\"สามสัญลักษณ์ ต้องแม่น\"</div>\n    </div>\n    <div class=\"section examtip\">\n      <div class=\"sec-head\"><span class=\"dot\"></span>🎯 ข้อสอบชอบออก</div>\n      <p>ท้ายข้อสอบมักมีคำถามสั้นแต่หลอกสัญลักษณ์ ถ้าจำสามแกนนี้ได้ จะลดพลาดได้มาก</p>\n    </div>\n    <div class=\"section checklist\">\n      <div class=\"sec-head\"><span class=\"dot\"></span>☑ Before You Submit</div>\n      <ul>\n      <li>จำ intersection union difference</li>\n      <li>จำเซตว่างเป็นสับเซต</li>\n      <li>จำ complement ก่อนนับ</li>\n      </ul>\n    </div>\n    <div class=\"pagefoot\">SetTheoryRescueKit Rescue Kit · เปิดก่อนสอบ 10 นาที</div>\n  </div>"
    }
  ]
}