{
  "id": "stat",
  "name": "Statistics",
  "th": "สถิติ",
  "desc": "Data Types · StemLeafHistogram · BoxPlotOutliers",
  "glyph": "x̄",
  "accent": "#9333ea",
  "parts": [
    {
      "id": "stat-p1",
      "num": "PART 1",
      "name": "Data Types",
      "th": "Data Types",
      "cardCount": 2,
      "accent": "#9333ea",
      "gridHTML": "<div class=\"card\" data-accent=\"blue\">\n    <div class=\"card-head\">\n      <div class=\"eyebrow\">PART 1 · Data Types · 🔵 Concept</div>\n      <div class=\"title\">ประเภทข้อมูล</div>\n    </div>\n    <div class=\"trigger-box\">\n      <div class=\"ic\">🎯</div>\n      <div class=\"txt\">ตัวเลขคำนวณได้ = เชิงปริมาณ; จัดกลุ่ม = เชิงคุณภาพ</div>\n    </div>\n    <div class=\"section when\">\n      <div class=\"sec-head\"><span class=\"dot\"></span>👀 เมื่อเจอโจทย์แบบนี้</div>\n      <ul>\n      <li>ส่วนสูง 165 ซม. เป็นข้อมูลแบบใด</li>\n      <li>รหัสนักเรียน 65021 เป็นข้อมูลแบบใด</li>\n      </ul>\n    </div>\n    <div class=\"section how\">\n      <div class=\"sec-head\"><span class=\"dot\"></span>✅ วิธีคิด</div>\n      <ol>\n      <li>ดูว่าค่ามีความหมายเชิงจำนวนหรือไม่</li>\n      <li>ถ้าบวก ลบ คูณ หารแล้วแปลผลได้ = เชิงปริมาณ</li>\n      <li>ถ้าเป็นชื่อ กลุ่ม รหัส = เชิงคุณภาพ</li>\n      </ol>\n    </div>\n    <div class=\"section mistake\">\n      <div class=\"sec-head\"><span class=\"dot\"></span>❌ จุดที่พลาดบ่อย</div>\n      <ul>\n      <li>คิดว่าเกรดเฉลี่ย 4.0 เป็นเชิงปริมาณเสมอ</li>\n      <li>เอาข้อมูลรหัสไปหาค่าเฉลี่ย</li>\n      </ul>\n    </div>\n    <div class=\"section hack\">\n      <div class=\"sec-head\"><span class=\"dot\"></span>🧠 เทคนิคจำ</div>\n      <div class=\"txt\">\"ตัวเลขมีความหมายค่อยนับ\"</div>\n    </div>\n    <div class=\"section examtip\">\n      <div class=\"sec-head\"><span class=\"dot\"></span>🎯 ข้อสอบชอบออก</div>\n      <p>ข้อสอบชอบหลอกด้วยเลขที่เป็นแค่รหัส เช่น เบอร์โทรศัพท์หรือรหัสนักเรียน ให้จำว่าไม่ใช่ตัวเลขสำหรับคำนวณเสมอ</p>\n    </div>\n    <div class=\"section checklist\">\n      <div class=\"sec-head\"><span class=\"dot\"></span>☑ Before You Submit</div>\n      <ul>\n      <li>บวกหารแล้วมีความหมายไหม</li>\n      <li>เป็นค่าแทนกลุ่มหรือไม่</li>\n      </ul>\n    </div>\n    <div class=\"pagefoot\">StatisticsRescue Kit · เปิดก่อนสอบ 10 นาที</div>\n  </div>\n\n\n  <div class=\"card\" data-accent=\"green\">\n    <div class=\"card-head\">\n      <div class=\"eyebrow\">PART 1 · Data Types · 🔵 Concept</div>\n      <div class=\"title\">ปฐมภูมิ-ทุติยภูมิ</div>\n    </div>\n    <div class=\"trigger-box\">\n      <div class=\"ic\">🎯</div>\n      <div class=\"txt\">เก็บเอง = ปฐมภูมิ; เอาของคนอื่น = ทุติยภูมิ</div>\n    </div>\n    <div class=\"section when\">\n      <div class=\"sec-head\"><span class=\"dot\"></span>👀 เมื่อเจอโจทย์แบบนี้</div>\n      <ul>\n      <li>สัมภาษณ์เพื่อนเรื่องเวลานอน</li>\n      <li>ใช้สถิติจากกระทรวงศึกษาธิการ</li>\n      </ul>\n    </div>\n    <div class=\"section how\">\n      <div class=\"sec-head\"><span class=\"dot\"></span>✅ วิธีคิด</div>\n      <ol>\n      <li>ถ้าเราออกไปเก็บเอง จัดเป็นปฐมภูมิ</li>\n      <li>ถ้าใช้ข้อมูลที่มีคนรวบรวมแล้ว จัดเป็นทุติยภูมิ</li>\n      <li>ดูที่แหล่งที่มาของข้อมูลก่อนตอบ</li>\n      </ol>\n    </div>\n    <div class=\"section mistake\">\n      <div class=\"sec-head\"><span class=\"dot\"></span>❌ จุดที่พลาดบ่อย</div>\n      <ul>\n      <li>สับสนว่าข้อมูลในเว็บทุกอย่างเป็นปฐมภูมิ</li>\n      <li>ลืมแยกผู้เก็บข้อมูลกับผู้ใช้ข้อมูล</li>\n      </ul>\n    </div>\n    <div class=\"section hack\">\n      <div class=\"sec-head\"><span class=\"dot\"></span>🧠 เทคนิคจำ</div>\n      <div class=\"txt\">\"เก็บเอง = primary\"</div>\n    </div>\n    <div class=\"section examtip\">\n      <div class=\"sec-head\"><span class=\"dot\"></span>🎯 ข้อสอบชอบออก</div>\n      <p>มักออกให้แยกว่าใครเป็นคนเก็บข้อมูลจริง ไม่ใช่แค่ว่าเราเอามาใช้จากที่ไหน</p>\n    </div>\n    <div class=\"section checklist\">\n      <div class=\"sec-head\"><span class=\"dot\"></span>☑ Before You Submit</div>\n      <ul>\n      <li>ใครเก็บข้อมูลจริง</li>\n      <li>ข้อมูลมาจากงานสำรวจเดิมหรือไม่</li>\n      </ul>\n    </div>\n    <div class=\"pagefoot\">StatisticsRescue Kit · เปิดก่อนสอบ 10 นาที</div>\n  </div>"
    },
    {
      "id": "stat-p2",
      "num": "PART 2",
      "name": "StemLeafHistogram",
      "th": "StemLeafHistogram",
      "cardCount": 2,
      "accent": "#9333ea",
      "gridHTML": "<div class=\"card\" data-accent=\"blue\">\n    <div class=\"card-head\">\n      <div class=\"eyebrow\">PART 2 · StemLeafHistogram · 🔵 Concept</div>\n      <div class=\"title\">ต้น-ใบ</div>\n    </div>\n    <div class=\"trigger-box\">\n      <div class=\"ic\">🎯</div>\n      <div class=\"txt\">ต้นคือหลักสิบ ใบคือหลักหน่วย</div>\n    </div>\n    <div class=\"section when\">\n      <div class=\"sec-head\"><span class=\"dot\"></span>👀 เมื่อเจอโจทย์แบบนี้</div>\n      <ul>\n      <li>ข้อมูล 12, 15, 18 เขียนแผนภาพต้น-ใบ</li>\n      <li>อ่านค่ามัธยฐานจากแผนภาพต้น-ใบ</li>\n      </ul>\n    </div>\n    <div class=\"section how\">\n      <div class=\"sec-head\"><span class=\"dot\"></span>✅ วิธีคิด</div>\n      <ol>\n      <li>แยกหลักสิบเป็นต้น</li>\n      <li>แยกหลักหน่วยเป็นใบ</li>\n      <li>เรียงใบจากน้อยไปมาก</li>\n      </ol>\n    </div>\n    <div class=\"section mistake\">\n      <div class=\"sec-head\"><span class=\"dot\"></span>❌ จุดที่พลาดบ่อย</div>\n      <ul>\n      <li>สลับต้นกับใบ</li>\n      <li>อ่านค่าผิดเพราะไม่เรียงใบ</li>\n      </ul>\n    </div>\n    <div class=\"section hack\">\n      <div class=\"sec-head\"><span class=\"dot\"></span>🧠 เทคนิคจำ</div>\n      <div class=\"txt\">\"ต้นสิบ ใบหน่วย\"</div>\n    </div>\n    <div class=\"section examtip\">\n      <div class=\"sec-head\"><span class=\"dot\"></span>🎯 ข้อสอบชอบออก</div>\n      <p>ข้อสอบชอบให้แปลข้อมูลเร็วจากภาพนี้ คิดเหมือนฮิสโทแกรมที่ตะแคงข้าง แล้วอ่านการกระจายได้ทันที</p>\n    </div>\n    <div class=\"section checklist\">\n      <div class=\"sec-head\"><span class=\"dot\"></span>☑ Before You Submit</div>\n      <ul>\n      <li>ต้นอยู่ซ้าย</li>\n      <li>ใบเรียงจากน้อยไปมาก</li>\n      </ul>\n    </div>\n    <div class=\"pagefoot\">StatisticsRescue Kit · เปิดก่อนสอบ 10 นาที</div>\n  </div>\n\n\n  <div class=\"card\" data-accent=\"green\">\n    <div class=\"card-head\">\n      <div class=\"eyebrow\">PART 2 · StemLeafHistogram · 🔵 Concept</div>\n      <div class=\"title\">ฮิสโทแกรม</div>\n    </div>\n    <div class=\"trigger-box\">\n      <div class=\"ic\">🎯</div>\n      <div class=\"txt\">แท่งต้องติดกัน แกนนอนคือช่วงข้อมูล</div>\n    </div>\n    <div class=\"section when\">\n      <div class=\"sec-head\"><span class=\"dot\"></span>👀 เมื่อเจอโจทย์แบบนี้</div>\n      <ul>\n      <li>ดูการกระจายคะแนนจากฮิสโทแกรม</li>\n      <li>หาแท่งช่วงความถี่สูงสุด</li>\n      </ul>\n    </div>\n    <div class=\"section how\">\n      <div class=\"sec-head\"><span class=\"dot\"></span>✅ วิธีคิด</div>\n      <ol>\n      <li>อ่านขอบล่าง-ขอบบนบนแกนนอน</li>\n      <li>ดูความสูงแท่งเป็นความถี่</li>\n      <li>แท่งต้องชิดกันไม่มีช่องว่าง</li>\n      </ol>\n    </div>\n    <div class=\"section mistake\">\n      <div class=\"sec-head\"><span class=\"dot\"></span>❌ จุดที่พลาดบ่อย</div>\n      <ul>\n      <li>วาดแท่งมีช่องว่างเหมือน bar chart</li>\n      <li>คิดว่าความสูงแท่งคือค่าข้อมูล</li>\n      </ul>\n    </div>\n    <div class=\"section hack\">\n      <div class=\"sec-head\"><span class=\"dot\"></span>🧠 เทคนิคจำ</div>\n      <div class=\"txt\">\"แท่งชิด = histogram\"</div>\n    </div>\n    <div class=\"section examtip\">\n      <div class=\"sec-head\"><span class=\"dot\"></span>🎯 ข้อสอบชอบออก</div>\n      <p>ถ้าโจทย์ถามความถี่รวม อย่ามองแค่ความสูงแท่ง ให้รวมความถี่หรือมองพื้นที่แท่งตามที่โจทย์กำหนด</p>\n    </div>\n    <div class=\"section checklist\">\n      <div class=\"sec-head\"><span class=\"dot\"></span>☑ Before You Submit</div>\n      <ul>\n      <li>แท่งชิดกันไหม</li>\n      <li>แกนนอนเป็นช่วงชั้นหรือไม่</li>\n      </ul>\n    </div>\n    <div class=\"pagefoot\">StatisticsRescue Kit · เปิดก่อนสอบ 10 นาที</div>\n  </div>"
    },
    {
      "id": "stat-p3",
      "num": "PART 3",
      "name": "BoxPlotOutliers",
      "th": "BoxPlotOutliers",
      "cardCount": 4,
      "accent": "#9333ea",
      "gridHTML": "<div class=\"card\" data-accent=\"blue\">\n    <div class=\"card-head\">\n      <div class=\"eyebrow\">PART 3 · BoxPlotOutliers · 🔵 Concept</div>\n      <div class=\"title\">ห้าค่าหลัก</div>\n    </div>\n    <div class=\"trigger-box\">\n      <div class=\"ic\">🎯</div>\n      <div class=\"txt\">Min Q1 Median Q3 Max คือโครงสร้างกล่อง</div>\n    </div>\n    <div class=\"section when\">\n      <div class=\"sec-head\"><span class=\"dot\"></span>👀 เมื่อเจอโจทย์แบบนี้</div>\n      <ul>\n      <li>อ่านค่ากล่องจากแผนภาพ box plot</li>\n      <li>เปรียบเทียบข้อมูลสองกลุ่ม</li>\n      </ul>\n    </div>\n    <div class=\"section how\">\n      <div class=\"sec-head\"><span class=\"dot\"></span>✅ วิธีคิด</div>\n      <ol>\n      <li>หาค่า Min และ Max ที่ปลายหนวด</li>\n      <li>หา Q1, Q2, Q3 จากตำแหน่งควอร์ไทล์</li>\n      <li>เรียงจากน้อยไปมากเสมอ</li>\n      </ol>\n    </div>\n    <div class=\"section mistake\">\n      <div class=\"sec-head\"><span class=\"dot\"></span>❌ จุดที่พลาดบ่อย</div>\n      <ul>\n      <li>สลับ Q2 กับค่าเฉลี่ย</li>\n      <li>คิดว่าหนวดคือช่วงข้อมูลเท่ากันทุกส่วน</li>\n      </ul>\n    </div>\n    <div class=\"section hack\">\n      <div class=\"sec-head\"><span class=\"dot\"></span>🧠 เทคนิคจำ</div>\n      <div class=\"txt\">\"ห้าเลข จำให้ครบ\"</div>\n    </div>\n    <div class=\"section examtip\">\n      <div class=\"sec-head\"><span class=\"dot\"></span>🎯 ข้อสอบชอบออก</div>\n      <p>ข้อสอบชอบให้ดูแผนภาพแล้วสรุปเร็วว่า median อยู่ตรงไหนและช่วงข้อมูลกว้างแค่ไหน อย่ารีบอ่านผิดตำแหน่ง</p>\n    </div>\n    <div class=\"section checklist\">\n      <div class=\"sec-head\"><span class=\"dot\"></span>☑ Before You Submit</div>\n      <ul>\n      <li>Min และ Max ถูกไหม</li>\n      <li>Q2 คือ median ใช่หรือไม่</li>\n      </ul>\n    </div>\n    <div class=\"pagefoot\">StatisticsRescue Kit · เปิดก่อนสอบ 10 นาที</div>\n  </div>\n\n\n  <div class=\"card\" data-accent=\"green\">\n    <div class=\"card-head\">\n      <div class=\"eyebrow\">PART 3 · BoxPlotOutliers · 🔵 Concept</div>\n      <div class=\"title\">สี่ช่วงเท่ากัน</div>\n    </div>\n    <div class=\"trigger-box\">\n      <div class=\"ic\">🎯</div>\n      <div class=\"txt\">แต่ละช่วงมีข้อมูล 25% เท่ากัน</div>\n    </div>\n    <div class=\"section when\">\n      <div class=\"sec-head\"><span class=\"dot\"></span>👀 เมื่อเจอโจทย์แบบนี้</div>\n      <ul>\n      <li>ช่วง Min ถึง Q1</li>\n      <li>ช่วง Q1 ถึง Q2</li>\n      </ul>\n    </div>\n    <div class=\"section how\">\n      <div class=\"sec-head\"><span class=\"dot\"></span>✅ วิธีคิด</div>\n      <ol>\n      <li>จำว่ากล่องและหนวดแบ่งข้อมูลเป็น 4 ส่วน</li>\n      <li>แต่ละส่วนมีข้อมูลเท่ากัน 25%</li>\n      <li>ความยาวช่วงไม่เท่ากับจำนวนคนเสมอ</li>\n      </ol>\n    </div>\n    <div class=\"section mistake\">\n      <div class=\"sec-head\"><span class=\"dot\"></span>❌ จุดที่พลาดบ่อย</div>\n      <ul>\n      <li>คิดว่าช่วงยาวกว่ามีคนมากกว่า</li>\n      <li>คิดว่าช่วงสั้นกว่าคนน้อยกว่า</li>\n      </ul>\n    </div>\n    <div class=\"section hack\">\n      <div class=\"sec-head\"><span class=\"dot\"></span>🧠 เทคนิคจำ</div>\n      <div class=\"txt\">\"ยาวไม่แปลว่าคนเยอะ\"</div>\n    </div>\n    <div class=\"section examtip\">\n      <div class=\"sec-head\"><span class=\"dot\"></span>🎯 ข้อสอบชอบออก</div>\n      <p>ออกบ่อยมากเรื่องตีความความยาวหนวดกับกล่อง ให้ตอบตาม 'ความกระจาย' ไม่ใช่จำนวนคน</p>\n    </div>\n    <div class=\"section checklist\">\n      <div class=\"sec-head\"><span class=\"dot\"></span>☑ Before You Submit</div>\n      <ul>\n      <li>มี 4 ส่วนเท่าๆ กัน</li>\n      <li>อย่าใช้ความยาวแทนจำนวนคน</li>\n      </ul>\n    </div>\n    <div class=\"pagefoot\">StatisticsRescue Kit · เปิดก่อนสอบ 10 นาที</div>\n  </div>\n\n\n  <div class=\"card\" data-accent=\"orange\">\n    <div class=\"card-head\">\n      <div class=\"eyebrow\">PART 3 · BoxPlotOutliers · 🟢 Formula</div>\n      <div class=\"title\">IQR และค่านอกกลุ่ม</div>\n    </div>\n    <div class=\"trigger-box\">\n      <div class=\"ic\">🎯</div>\n      <div class=\"txt\">ต่ำกว่า Q1 ลบ 1.5IQR หรือสูงกว่า Q3 บวก 1.5IQR</div>\n    </div>\n    <div class=\"section when\">\n      <div class=\"sec-head\"><span class=\"dot\"></span>👀 เมื่อเจอโจทย์แบบนี้</div>\n      <ul>\n      <li>หา outlier จากชุดข้อมูล</li>\n      <li>เช็กจุดผิดปกติใน box plot</li>\n      </ul>\n    </div>\n    <div class=\"section how\">\n      <div class=\"sec-head\"><span class=\"dot\"></span>✅ วิธีคิด</div>\n      <ol>\n      <li>หา IQR = Q3 - Q1</li>\n      <li>หาขอบล่าง = Q1 - 1.5(IQR)</li>\n      <li>หาขอบบน = Q3 + 1.5(IQR)</li>\n      </ol>\n    </div>\n    <div class=\"section mistake\">\n      <div class=\"sec-head\"><span class=\"dot\"></span>❌ จุดที่พลาดบ่อย</div>\n      <ul>\n      <li>ลืมลบ Q3 - Q1 ก่อน</li>\n      <li>เอา 1.5 ไปคูณผิดตำแหน่ง</li>\n      </ul>\n    </div>\n    <div class=\"section hack\">\n      <div class=\"sec-head\"><span class=\"dot\"></span>🧠 เทคนิคจำ</div>\n      <div class=\"txt\">\"IQR ก่อน แล้วค่อยบวกหรือลบ\"</div>\n    </div>\n    <div class=\"section examtip\">\n      <div class=\"sec-head\"><span class=\"dot\"></span>🎯 ข้อสอบชอบออก</div>\n      <p>โจทย์มักให้ข้อมูลหลายตัวแล้วถามค่าผิดปกติ ตัดสินด้วยเกณฑ์ 1.5IQR เท่านั้น ไม่ใช่ดูด้วยตาอย่างเดียว</p>\n    </div>\n    <div class=\"section checklist\">\n      <div class=\"sec-head\"><span class=\"dot\"></span>☑ Before You Submit</div>\n      <ul>\n      <li>คำนวณ IQR ก่อน</li>\n      <li>เทียบกับขอบล่างและขอบบน</li>\n      </ul>\n    </div>\n    <div class=\"pagefoot\">StatisticsRescue Kit · เปิดก่อนสอบ 10 นาที</div>\n  </div>\n\n\n  <div class=\"card\" data-accent=\"purple\">\n    <div class=\"card-head\">\n      <div class=\"eyebrow\">PART 3 · BoxPlotOutliers · 🟣 Exam Tip</div>\n      <div class=\"title\">แปลความกว้าง</div>\n    </div>\n    <div class=\"trigger-box\">\n      <div class=\"ic\">🎯</div>\n      <div class=\"txt\">ช่วงกว้าง = กระจายมาก; ช่วงแคบ = กระจุกตัว</div>\n    </div>\n    <div class=\"section when\">\n      <div class=\"sec-head\"><span class=\"dot\"></span>👀 เมื่อเจอโจทย์แบบนี้</div>\n      <ul>\n      <li>ดูช่วง Q1 ถึง Q3</li>\n      <li>เทียบความกว้างของหนวดสองข้าง</li>\n      </ul>\n    </div>\n    <div class=\"section how\">\n      <div class=\"sec-head\"><span class=\"dot\"></span>✅ วิธีคิด</div>\n      <ol>\n      <li>มองความยาวช่วงเป็นการกระจาย</li>\n      <li>ช่วงสั้นแปลว่าข้อมูลเกาะกลุ่ม</li>\n      <li>ช่วงยาวแปลว่าข้อมูลห่างกัน</li>\n      </ol>\n    </div>\n    <div class=\"section mistake\">\n      <div class=\"sec-head\"><span class=\"dot\"></span>❌ จุดที่พลาดบ่อย</div>\n      <ul>\n      <li>คิดว่าช่วงกว้างแปลว่าคนเยอะ</li>\n      <li>สรุปผิดเรื่องความหนาแน่นของข้อมูล</li>\n      </ul>\n    </div>\n    <div class=\"section hack\">\n      <div class=\"sec-head\"><span class=\"dot\"></span>🧠 เทคนิคจำ</div>\n      <div class=\"txt\">\"ยาวคือกระจาย ไม่ใช่จำนวน\"</div>\n    </div>\n    <div class=\"section examtip\">\n      <div class=\"sec-head\"><span class=\"dot\"></span>🎯 ข้อสอบชอบออก</div>\n      <p>ข้อสอบชอบหลอกให้สรุปเรื่องความหนาแน่นจากความยาวของ box plot ให้ตอบเรื่อง 'กระจาย' เท่านั้น</p>\n    </div>\n    <div class=\"section checklist\">\n      <div class=\"sec-head\"><span class=\"dot\"></span>☑ Before You Submit</div>\n      <ul>\n      <li>พูดถึงการกระจาย</li>\n      <li>ไม่ตีความเป็นจำนวนคน</li>\n      </ul>\n    </div>\n    <div class=\"pagefoot\">StatisticsRescue Kit · เปิดก่อนสอบ 10 นาที</div>\n  </div>"
    },
    {
      "id": "stat-p4",
      "num": "PART 4",
      "name": "CentralTendency",
      "th": "CentralTendency",
      "cardCount": 4,
      "accent": "#9333ea",
      "gridHTML": "<div class=\"card\" data-accent=\"blue\">\n    <div class=\"card-head\">\n      <div class=\"eyebrow\">PART 4 · CentralTendency · 🔵 Concept</div>\n      <div class=\"title\">ค่าเฉลี่ย</div>\n    </div>\n    <div class=\"trigger-box\">\n      <div class=\"ic\">🎯</div>\n      <div class=\"txt\">Mean รวมทุกตัวแล้วหารจำนวนข้อมูล</div>\n    </div>\n    <div class=\"section when\">\n      <div class=\"sec-head\"><span class=\"dot\"></span>👀 เมื่อเจอโจทย์แบบนี้</div>\n      <ul>\n      <li>โจทย์ให้ข้อมูลดิบ \\(x_1,x_2,\\dots,x_N\\) แล้วถามค่าเฉลี่ย</li>\n      <li>มีค่า outlier แล้วต้องดูว่าควรใช้ mean หรือไม่</li>\n      </ul>\n    </div>\n    <div class=\"section how\">\n      <div class=\"sec-head\"><span class=\"dot\"></span>✅ วิธีคิด</div>\n      <ol>\n      <li>บวกข้อมูลทุกตัว</li>\n      <li>หารด้วยจำนวนข้อมูล \\(N\\)</li>\n      <li>ใช้ \\(\\bar{x}=\\frac{\\Sigma x_i}{N}\\)</li>\n      </ol>\n    </div>\n    <div class=\"section mistake\">\n      <div class=\"sec-head\"><span class=\"dot\"></span>❌ จุดที่พลาดบ่อย</div>\n      <ul>\n      <li>ลืมเรียงข้อมูลก่อนหามัธยฐาน</li>\n      <li>เอาค่า outlier ไปดึง mean จนตีความผิด</li>\n      </ul>\n    </div>\n    <div class=\"section hack\">\n      <div class=\"sec-head\"><span class=\"dot\"></span>🧠 เทคนิคจำ</div>\n      <div class=\"txt\">\"Mean รับทุกตัว\"</div>\n    </div>\n    <div class=\"section examtip\">\n      <div class=\"sec-head\"><span class=\"dot\"></span>🎯 ข้อสอบชอบออก</div>\n      <p>ข้อสอบชอบให้ข้อมูลมีค่าหลุดสุดโต่งแล้วถามว่าค่ากลางใดเหมาะกว่า ถ้ามี outlier มากให้ระวัง mean เพี้ยนและมักควรใช้ median แทน</p>\n    </div>\n    <div class=\"section checklist\">\n      <div class=\"sec-head\"><span class=\"dot\"></span>☑ Before You Submit</div>\n      <ul>\n      <li>เช็กว่าข้อมูลครบทุกตัว</li>\n      <li>เช็กว่าโจทย์ถาม mean หรือกลางที่เหมาะสม</li>\n      </ul>\n    </div>\n    <div class=\"pagefoot\">StatisticsRescue Kit · เปิดก่อนสอบ 10 นาที</div>\n  </div>\n\n\n  <div class=\"card\" data-accent=\"green\">\n    <div class=\"card-head\">\n      <div class=\"eyebrow\">PART 4 · CentralTendency · 🟢 Formula</div>\n      <div class=\"title\">มัธยฐาน</div>\n    </div>\n    <div class=\"trigger-box\">\n      <div class=\"ic\">🎯</div>\n      <div class=\"txt\">Median คือค่ากลางหลังเรียงจากน้อยไปมาก</div>\n    </div>\n    <div class=\"section when\">\n      <div class=\"sec-head\"><span class=\"dot\"></span>👀 เมื่อเจอโจทย์แบบนี้</div>\n      <ul>\n      <li>ข้อมูลมีจำนวนคี่แล้วถามค่ากลาง</li>\n      <li>ข้อมูลมีจำนวนคู่แล้วถามค่ากลาง</li>\n      </ul>\n    </div>\n    <div class=\"section how\">\n      <div class=\"sec-head\"><span class=\"dot\"></span>✅ วิธีคิด</div>\n      <ol>\n      <li>เรียงข้อมูลจากน้อยไปมาก</li>\n      <li>หาตำแหน่ง \\(\\frac{N+1}{2}\\)</li>\n      <li>ถ้าเป็นคู่ให้เฉลี่ย 2 ตัวกลาง</li>\n      </ol>\n    </div>\n    <div class=\"section mistake\">\n      <div class=\"sec-head\"><span class=\"dot\"></span>❌ จุดที่พลาดบ่อย</div>\n      <ul>\n      <li>หาค่ากลางจากข้อมูลที่ยังไม่เรียง</li>\n      <li>สับสน median กับ mean</li>\n      </ul>\n    </div>\n    <div class=\"section hack\">\n      <div class=\"sec-head\"><span class=\"dot\"></span>🧠 เทคนิคจำ</div>\n      <div class=\"txt\">\"กลางต้องเรียงก่อน\"</div>\n    </div>\n    <div class=\"section examtip\">\n      <div class=\"sec-head\"><span class=\"dot\"></span>🎯 ข้อสอบชอบออก</div>\n      <p>โจทย์ชอบแฝงข้อมูลที่เรียงสุ่มมา ถ้าไม่เรียงก่อนจะตอบผิดทันที โดยเฉพาะข้อที่ถามตำแหน่งกลางของชุดข้อมูล</p>\n    </div>\n    <div class=\"section checklist\">\n      <div class=\"sec-head\"><span class=\"dot\"></span>☑ Before You Submit</div>\n      <ul>\n      <li>เรียงข้อมูลแล้วหรือยัง</li>\n      <li>ตำแหน่งกลางเป็นตัวเดียวหรือ 2 ตัว</li>\n      </ul>\n    </div>\n    <div class=\"pagefoot\">StatisticsRescue Kit · เปิดก่อนสอบ 10 นาที</div>\n  </div>\n\n\n  <div class=\"card\" data-accent=\"orange\">\n    <div class=\"card-head\">\n      <div class=\"eyebrow\">PART 4 · CentralTendency · 🔵 Concept</div>\n      <div class=\"title\">ฐานนิยม</div>\n    </div>\n    <div class=\"trigger-box\">\n      <div class=\"ic\">🎯</div>\n      <div class=\"txt\">Mode คือค่าที่ซ้ำมากที่สุด</div>\n    </div>\n    <div class=\"section when\">\n      <div class=\"sec-head\"><span class=\"dot\"></span>👀 เมื่อเจอโจทย์แบบนี้</div>\n      <ul>\n      <li>โจทย์ถามค่าที่พบมากสุดในชุดข้อมูล</li>\n      <li>ข้อมูลอาจมีหลายฐานนิยม</li>\n      </ul>\n    </div>\n    <div class=\"section how\">\n      <div class=\"sec-head\"><span class=\"dot\"></span>✅ วิธีคิด</div>\n      <ol>\n      <li>นับความถี่ของแต่ละค่า</li>\n      <li>เลือกค่าที่ถี่ที่สุด</li>\n      <li>ถ้าเท่ากันหลายค่าให้ตอบหลาย mode</li>\n      </ol>\n    </div>\n    <div class=\"section mistake\">\n      <div class=\"sec-head\"><span class=\"dot\"></span>❌ จุดที่พลาดบ่อย</div>\n      <ul>\n      <li>คิดว่า mode ต้องมีแค่ค่าเดียวเสมอ</li>\n      <li>ดูแค่ค่าที่มากสุด ไม่ใช่ค่าที่ซ้ำมากสุด</li>\n      </ul>\n    </div>\n    <div class=\"section hack\">\n      <div class=\"sec-head\"><span class=\"dot\"></span>🧠 เทคนิคจำ</div>\n      <div class=\"txt\">\"ซ้ำมากสุดคือ mode\"</div>\n    </div>\n    <div class=\"section examtip\">\n      <div class=\"sec-head\"><span class=\"dot\"></span>🎯 ข้อสอบชอบออก</div>\n      <p>ข้อสอบชอบให้ตารางความถี่หรือกราฟแท่งแล้วถาม mode ต้องอ่านจากจำนวนครั้งที่เกิด ไม่ใช่ค่าตัวเลขที่ใหญ่ที่สุด</p>\n    </div>\n    <div class=\"section checklist\">\n      <div class=\"sec-head\"><span class=\"dot\"></span>☑ Before You Submit</div>\n      <ul>\n      <li>นับความถี่ครบทุกค่า</li>\n      <li>แยกให้ได้ว่าค่ามากสุดไม่เท่าค่าซ้ำสุดเสมอ</li>\n      </ul>\n    </div>\n    <div class=\"pagefoot\">StatisticsRescue Kit · เปิดก่อนสอบ 10 นาที</div>\n  </div>\n\n\n  <div class=\"card\" data-accent=\"purple\">\n    <div class=\"card-head\">\n      <div class=\"eyebrow\">PART 4 · CentralTendency · 🟣 Exam Tip</div>\n      <div class=\"title\">mean sum zero</div>\n    </div>\n    <div class=\"trigger-box\">\n      <div class=\"ic\">🎯</div>\n      <div class=\"txt\">ผลรวมส่วนเบี่ยงเบนจาก mean ต้องเป็นศูนย์</div>\n    </div>\n    <div class=\"section when\">\n      <div class=\"sec-head\"><span class=\"dot\"></span>👀 เมื่อเจอโจทย์แบบนี้</div>\n      <ul>\n      <li>ถามสมบัติของ mean</li>\n      <li>ตรวจคำตอบที่หาค่าเฉลี่ย</li>\n      </ul>\n    </div>\n    <div class=\"section how\">\n      <div class=\"sec-head\"><span class=\"dot\"></span>✅ วิธีคิด</div>\n      <ol>\n      <li>ใช้ \\(\\bar{x}\\) เป็นจุดอ้างอิง</li>\n      <li>รวม \\((x_i-\\bar{x})\\) ทุกตัว</li>\n      <li>จำว่าได้ศูนย์เสมอ</li>\n      </ol>\n    </div>\n    <div class=\"section mistake\">\n      <div class=\"sec-head\"><span class=\"dot\"></span>❌ จุดที่พลาดบ่อย</div>\n      <ul>\n      <li>ลืมว่าส่วนเบี่ยงเบนบวกกับลบหักล้างกัน</li>\n      <li>เอาไปใช้กับ median แทน mean</li>\n      </ul>\n    </div>\n    <div class=\"section hack\">\n      <div class=\"sec-head\"><span class=\"dot\"></span>🧠 เทคนิคจำ</div>\n      <div class=\"txt\">\"เบี่ยงเบนรวมเป็นศูนย์\"</div>\n    </div>\n    <div class=\"section examtip\">\n      <div class=\"sec-head\"><span class=\"dot\"></span>🎯 ข้อสอบชอบออก</div>\n      <p>โจทย์ชอบถามสมบัติสั้นๆ เพื่อเช็กความเข้าใจ ถ้าเห็นผลรวมส่วนเบี่ยงเบน ให้ตอบ mean ทันที</p>\n    </div>\n    <div class=\"section checklist\">\n      <div class=\"sec-head\"><span class=\"dot\"></span>☑ Before You Submit</div>\n      <ul>\n      <li>ใช้ mean เป็นจุดกลาง</li>\n      <li>ผลรวมส่วนเบี่ยงเบนต้องเป็นศูนย์</li>\n      </ul>\n    </div>\n    <div class=\"pagefoot\">StatisticsRescue Kit · เปิดก่อนสอบ 10 นาที</div>\n  </div>"
    },
    {
      "id": "stat-p5",
      "num": "PART 5",
      "name": "PositionData",
      "th": "PositionData",
      "cardCount": 3,
      "accent": "#9333ea",
      "gridHTML": "<div class=\"card\" data-accent=\"blue\">\n    <div class=\"card-head\">\n      <div class=\"eyebrow\">PART 5 · PositionData · 🟢 Formula</div>\n      <div class=\"title\">เปอร์เซ็นไทล์</div>\n    </div>\n    <div class=\"trigger-box\">\n      <div class=\"ic\">🎯</div>\n      <div class=\"txt\">หาตำแหน่งด้วย \\(\\frac{r(N+1)}{100}\\)</div>\n    </div>\n    <div class=\"section when\">\n      <div class=\"sec-head\"><span class=\"dot\"></span>👀 เมื่อเจอโจทย์แบบนี้</div>\n      <ul>\n      <li>โจทย์ถาม \\(P_r\\) ของข้อมูลเรียงลำดับ</li>\n      <li>ต้องหาค่าร้อยละที่ r</li>\n      </ul>\n    </div>\n    <div class=\"section how\">\n      <div class=\"sec-head\"><span class=\"dot\"></span>✅ วิธีคิด</div>\n      <ol>\n      <li>เรียงข้อมูลก่อน</li>\n      <li>หาตำแหน่ง \\(P_r=\\frac{r(N+1)}{100}\\)</li>\n      <li>ถ้าตำแหน่งไม่เป็นจำนวนเต็มให้เทียบระหว่างสองค่า</li>\n      </ol>\n    </div>\n    <div class=\"section mistake\">\n      <div class=\"sec-head\"><span class=\"dot\"></span>❌ จุดที่พลาดบ่อย</div>\n      <ul>\n      <li>ลืม \\(+1\\) ใน \\(N+1\\)</li>\n      <li>หยิบค่าก่อนเรียงข้อมูล</li>\n      </ul>\n    </div>\n    <div class=\"section hack\">\n      <div class=\"sec-head\"><span class=\"dot\"></span>🧠 เทคนิคจำ</div>\n      <div class=\"txt\">\"ตำแหน่งใช้ N บวกหนึ่ง\"</div>\n    </div>\n    <div class=\"section examtip\">\n      <div class=\"sec-head\"><span class=\"dot\"></span>🎯 ข้อสอบชอบออก</div>\n      <p>ข้อสอบชอบหลอกที่ตำแหน่งเป็นทศนิยม ต้องเทียบบัญญัติไตรยางศ์หรือเฉลี่ยสองค่าติดกันตามตำแหน่ง</p>\n    </div>\n    <div class=\"section checklist\">\n      <div class=\"sec-head\"><span class=\"dot\"></span>☑ Before You Submit</div>\n      <ul>\n      <li>เรียงข้อมูลแล้วหรือยัง</li>\n      <li>ใส่ \\(N+1\\) ครบหรือไม่</li>\n      </ul>\n    </div>\n    <div class=\"pagefoot\">StatisticsRescue Kit · เปิดก่อนสอบ 10 นาที</div>\n  </div>\n\n\n  <div class=\"card\" data-accent=\"green\">\n    <div class=\"card-head\">\n      <div class=\"eyebrow\">PART 5 · PositionData · 🟢 Formula</div>\n      <div class=\"title\">ควอไทล์</div>\n    </div>\n    <div class=\"trigger-box\">\n      <div class=\"ic\">🎯</div>\n      <div class=\"txt\">Quartile ใช้ตำแหน่ง \\(\\frac{r(N+1)}{4}\\)</div>\n    </div>\n    <div class=\"section when\">\n      <div class=\"sec-head\"><span class=\"dot\"></span>👀 เมื่อเจอโจทย์แบบนี้</div>\n      <ul>\n      <li>โจทย์ถาม \\(Q_1,Q_2,Q_3\\)</li>\n      <li>ต้องหาแบ่งข้อมูลเป็น 4 ส่วน</li>\n      </ul>\n    </div>\n    <div class=\"section how\">\n      <div class=\"sec-head\"><span class=\"dot\"></span>✅ วิธีคิด</div>\n      <ol>\n      <li>เรียงข้อมูล</li>\n      <li>หาตำแหน่ง \\(Q_r=\\frac{r(N+1)}{4}\\)</li>\n      <li>ถ้าตำแหน่งทศนิยมให้เทียบค่าระหว่างตำแหน่ง</li>\n      </ol>\n    </div>\n    <div class=\"section mistake\">\n      <div class=\"sec-head\"><span class=\"dot\"></span>❌ จุดที่พลาดบ่อย</div>\n      <ul>\n      <li>คิดว่า \\(Q_2\\) ไม่ใช่ median</li>\n      <li>สลับลำดับของ \\(Q_1,Q_2,Q_3\\)</li>\n      </ul>\n    </div>\n    <div class=\"section hack\">\n      <div class=\"sec-head\"><span class=\"dot\"></span>🧠 เทคนิคจำ</div>\n      <div class=\"txt\">\"สี่ส่วนใช้สี่หาร\"</div>\n    </div>\n    <div class=\"section examtip\">\n      <div class=\"sec-head\"><span class=\"dot\"></span>🎯 ข้อสอบชอบออก</div>\n      <p>โจทย์มักถามควอไทล์ร่วมกับ box plot ถ้าตำแหน่งอยู่ครึ่งทางระหว่างจุดใดสองจุด ให้เฉลี่ยสองค่านั้น</p>\n    </div>\n    <div class=\"section checklist\">\n      <div class=\"sec-head\"><span class=\"dot\"></span>☑ Before You Submit</div>\n      <ul>\n      <li>เรียงข้อมูล</li>\n      <li>หาควอไทล์ที่ตรงกับ r</li>\n      </ul>\n    </div>\n    <div class=\"pagefoot\">StatisticsRescue Kit · เปิดก่อนสอบ 10 นาที</div>\n  </div>\n\n\n  <div class=\"card\" data-accent=\"orange\">\n    <div class=\"card-head\">\n      <div class=\"eyebrow\">PART 5 · PositionData · 🟠 Trigger</div>\n      <div class=\"title\">Q2 เท่ามัธยฐาน</div>\n    </div>\n    <div class=\"trigger-box\">\n      <div class=\"ic\">🎯</div>\n      <div class=\"txt\">\\(Q_2\\) = \\(P_{50}\\) = Median</div>\n    </div>\n    <div class=\"section when\">\n      <div class=\"sec-head\"><span class=\"dot\"></span>👀 เมื่อเจอโจทย์แบบนี้</div>\n      <ul>\n      <li>โจทย์ถามค่ากลางด้วยชื่อหลายแบบ</li>\n      <li>ต้องเทียบควอไทล์กับเปอร์เซ็นไทล์</li>\n      </ul>\n    </div>\n    <div class=\"section how\">\n      <div class=\"sec-head\"><span class=\"dot\"></span>✅ วิธีคิด</div>\n      <ol>\n      <li>จำว่า \\(Q_2\\) คือจุดกึ่งกลาง</li>\n      <li>จำว่า \\(P_{50}\\) คือกึ่งกลางเหมือนกัน</li>\n      <li>สรุปว่าเท่ากับ median</li>\n      </ol>\n    </div>\n    <div class=\"section mistake\">\n      <div class=\"sec-head\"><span class=\"dot\"></span>❌ จุดที่พลาดบ่อย</div>\n      <ul>\n      <li>คิดว่าเป็นคนละสูตร</li>\n      <li>ตอบค่าต่างกันทั้งที่เป็นจุดเดียวกัน</li>\n      </ul>\n    </div>\n    <div class=\"section hack\">\n      <div class=\"sec-head\"><span class=\"dot\"></span>🧠 เทคนิคจำ</div>\n      <div class=\"txt\">\"ห้าสิบเปอร์เซ็นต์คือกลาง\"</div>\n    </div>\n    <div class=\"section examtip\">\n      <div class=\"sec-head\"><span class=\"dot\"></span>🎯 ข้อสอบชอบออก</div>\n      <p>ข้อสอบชอบให้เลือกสัญลักษณ์สับสน แต่จริงๆ สามตัวนี้แทนตำแหน่งเดียวกัน จึงให้ค่าเดียวกัน</p>\n    </div>\n    <div class=\"section checklist\">\n      <div class=\"sec-head\"><span class=\"dot\"></span>☑ Before You Submit</div>\n      <ul>\n      <li>ดูชื่อสัญลักษณ์ให้ชัด</li>\n      <li>จำสามตัวนี้เท่ากัน</li>\n      </ul>\n    </div>\n    <div class=\"pagefoot\">StatisticsRescue Kit · เปิดก่อนสอบ 10 นาที</div>\n  </div>"
    },
    {
      "id": "stat-p6",
      "num": "PART 6",
      "name": "Dispersion",
      "th": "Dispersion",
      "cardCount": 3,
      "accent": "#9333ea",
      "gridHTML": "<div class=\"card\" data-accent=\"blue\">\n    <div class=\"card-head\">\n      <div class=\"eyebrow\">PART 6 · Dispersion · 🔵 Concept</div>\n      <div class=\"title\">ความแปรปรวน</div>\n    </div>\n    <div class=\"trigger-box\">\n      <div class=\"ic\">🎯</div>\n      <div class=\"txt\">Variance คือ SD ยกกำลังสอง</div>\n    </div>\n    <div class=\"section when\">\n      <div class=\"sec-head\"><span class=\"dot\"></span>👀 เมื่อเจอโจทย์แบบนี้</div>\n      <ul>\n      <li>โจทย์ถาม \\(s^2\\) หรือ \\(\\sigma^2\\)</li>\n      <li>ต้องแปลงจาก SD เป็น variance</li>\n      </ul>\n    </div>\n    <div class=\"section how\">\n      <div class=\"sec-head\"><span class=\"dot\"></span>✅ วิธีคิด</div>\n      <ol>\n      <li>หาค่า SD ก่อนถ้าจำเป็น</li>\n      <li>ยกกำลังสองเพื่อได้ variance</li>\n      <li>จำว่า \\(Var=SD^2\\)</li>\n      </ol>\n    </div>\n    <div class=\"section mistake\">\n      <div class=\"sec-head\"><span class=\"dot\"></span>❌ จุดที่พลาดบ่อย</div>\n      <ul>\n      <li>คิดว่า variance กับ SD เหมือนกัน</li>\n      <li>ลืมยกกำลังสองตอนแปลง</li>\n      </ul>\n    </div>\n    <div class=\"section hack\">\n      <div class=\"sec-head\"><span class=\"dot\"></span>🧠 เทคนิคจำ</div>\n      <div class=\"txt\">\"แปรปรวนคือ SD²\"</div>\n    </div>\n    <div class=\"section examtip\">\n      <div class=\"sec-head\"><span class=\"dot\"></span>🎯 ข้อสอบชอบออก</div>\n      <p>ข้อสอบชอบให้สลับคำว่า SD, variance, \\(s^2\\), \\(\\sigma^2\\) ถ้าอ่านไม่ดีจะตอบผิดทันที</p>\n    </div>\n    <div class=\"section checklist\">\n      <div class=\"sec-head\"><span class=\"dot\"></span>☑ Before You Submit</div>\n      <ul>\n      <li>ดูหน่วยให้ถูก</li>\n      <li>เช็กว่าโจทย์ถาม square หรือไม่</li>\n      </ul>\n    </div>\n    <div class=\"pagefoot\">StatisticsRescue Kit · เปิดก่อนสอบ 10 นาที</div>\n  </div>\n\n\n  <div class=\"card\" data-accent=\"green\">\n    <div class=\"card-head\">\n      <div class=\"eyebrow\">PART 6 · Dispersion · 🟣 Exam Tip</div>\n      <div class=\"title\">ประชากรกับกลุ่มตัวอย่าง</div>\n    </div>\n    <div class=\"trigger-box\">\n      <div class=\"ic\">🎯</div>\n      <div class=\"txt\">ประชากรหาร \\(N\\) ตัวอย่างหาร \\(N-1\\)</div>\n    </div>\n    <div class=\"section when\">\n      <div class=\"sec-head\"><span class=\"dot\"></span>👀 เมื่อเจอโจทย์แบบนี้</div>\n      <ul>\n      <li>โจทย์ระบุ population</li>\n      <li>โจทย์ระบุ sample</li>\n      </ul>\n    </div>\n    <div class=\"section how\">\n      <div class=\"sec-head\"><span class=\"dot\"></span>✅ วิธีคิด</div>\n      <ol>\n      <li>ถ้าเป็นประชากรใช้ \\(N\\)</li>\n      <li>ถ้าเป็นกลุ่มตัวอย่างใช้ \\(N-1\\)</li>\n      <li>เลือกสูตรให้ตรงคำโจทย์</li>\n      </ol>\n    </div>\n    <div class=\"section mistake\">\n      <div class=\"sec-head\"><span class=\"dot\"></span>❌ จุดที่พลาดบ่อย</div>\n      <ul>\n      <li>ใช้หารผิดตัว</li>\n      <li>ไม่อ่านคำว่า sample หรือ population</li>\n      </ul>\n    </div>\n    <div class=\"section hack\">\n      <div class=\"sec-head\"><span class=\"dot\"></span>🧠 เทคนิคจำ</div>\n      <div class=\"txt\">\"ดู N หรือ N-1\"</div>\n    </div>\n    <div class=\"section examtip\">\n      <div class=\"sec-head\"><span class=\"dot\"></span>🎯 ข้อสอบชอบออก</div>\n      <p>ข้อสอบชอบซ่อนคำว่า sample ไว้ในประโยคยาวๆ ถ้าไม่จับคำนี้ สูตร variance จะผิดทันที</p>\n    </div>\n    <div class=\"section checklist\">\n      <div class=\"sec-head\"><span class=\"dot\"></span>☑ Before You Submit</div>\n      <ul>\n      <li>วงคำว่า sample/population</li>\n      <li>เลือกตัวหารให้ตรง</li>\n      </ul>\n    </div>\n    <div class=\"pagefoot\">StatisticsRescue Kit · เปิดก่อนสอบ 10 นาที</div>\n  </div>\n\n\n  <div class=\"card\" data-accent=\"orange\">\n    <div class=\"card-head\">\n      <div class=\"eyebrow\">PART 6 · Dispersion · 🟢 Formula</div>\n      <div class=\"title\">สูตรลัดวาเรียนซ์</div>\n    </div>\n    <div class=\"trigger-box\">\n      <div class=\"ic\">🎯</div>\n      <div class=\"txt\">ใช้ \\(\\frac{\\Sigma x_i^2}{N}-\\bar{x}^2\\) ได้เร็ว</div>\n    </div>\n    <div class=\"section when\">\n      <div class=\"sec-head\"><span class=\"dot\"></span>👀 เมื่อเจอโจทย์แบบนี้</div>\n      <ul>\n      <li>โจทย์ให้ตารางข้อมูลแล้วถาม variance</li>\n      <li>ต้องคำนวณเร็วในเวลาสั้น</li>\n      </ul>\n    </div>\n    <div class=\"section how\">\n      <div class=\"sec-head\"><span class=\"dot\"></span>✅ วิธีคิด</div>\n      <ol>\n      <li>หา \\(\\Sigma x_i^2\\)</li>\n      <li>หารด้วย \\(N\\)</li>\n      <li>ลบด้วย \\(\\bar{x}^2\\)</li>\n      </ol>\n    </div>\n    <div class=\"section mistake\">\n      <div class=\"sec-head\"><span class=\"dot\"></span>❌ จุดที่พลาดบ่อย</div>\n      <ul>\n      <li>เอา \\(\\bar{x}\\) ไปยกกำลังสองผิดตำแหน่ง</li>\n      <li>ลืมใช้ข้อมูลกำลังสองตั้งแต่แรก</li>\n      </ul>\n    </div>\n    <div class=\"section hack\">\n      <div class=\"sec-head\"><span class=\"dot\"></span>🧠 เทคนิคจำ</div>\n      <div class=\"txt\">\"สองค่าเฉลี่ยแล้วลบกัน\"</div>\n    </div>\n    <div class=\"section examtip\">\n      <div class=\"sec-head\"><span class=\"dot\"></span>🎯 ข้อสอบชอบออก</div>\n      <p>ข้อสอบชอบให้ข้อมูลหลายค่าและเวลาน้อย สูตรลัดนี้ช่วยลดการคำนวณได้มาก แต่ต้องไม่สลับกับ \\(\\left(\\frac{\\Sigma x_i}{N}\\right)^2\\)</p>\n    </div>\n    <div class=\"section checklist\">\n      <div class=\"sec-head\"><span class=\"dot\"></span>☑ Before You Submit</div>\n      <ul>\n      <li>เช็กว่าเป็น \\(x_i^2\\) ไม่ใช่ \\(x_i\\)</li>\n      <li>ลบ \\(\\bar{x}^2\\) ให้ถูกตำแหน่ง</li>\n      </ul>\n    </div>\n    <div class=\"pagefoot\">StatisticsRescue Kit · เปิดก่อนสอบ 10 นาที</div>\n  </div>"
    },
    {
      "id": "stat-p7",
      "num": "PART 7",
      "name": "Data Transformation",
      "th": "Data Transformation",
      "cardCount": 4,
      "accent": "#9333ea",
      "gridHTML": "<div class=\"card\" data-accent=\"blue\">\n    <div class=\"card-head\">\n      <div class=\"eyebrow\">PART 7 · Data Transformation · 🔵 Concept</div>\n      <div class=\"title\">สมการแปลงข้อมูล</div>\n    </div>\n    <div class=\"trigger-box\">\n      <div class=\"ic\">🎯</div>\n      <div class=\"txt\">แปลงทั้งก้อน ค่ากลางตามสูตร การกระจายดูแค่ตัวคูณ</div>\n    </div>\n    <div class=\"section when\">\n      <div class=\"sec-head\"><span class=\"dot\"></span>👀 เมื่อเจอโจทย์แบบนี้</div>\n      <ul>\n      <li>โจทย์ให้ \\(y=2x+10\\)</li>\n      <li>โจทย์ให้ \\(y=-3x+5\\)</li>\n      </ul>\n    </div>\n    <div class=\"section how\">\n      <div class=\"sec-head\"><span class=\"dot\"></span>✅ วิธีคิด</div>\n      <ol>\n      <li>แทนค่าในรูป \\(y=ax+b\\)</li>\n      <li>ค่ากลางใช้ \\(\\bar{y}=a\\bar{x}+b\\)</li>\n      <li>การกระจายใช้ตัวคูณเท่านั้น</li>\n      </ol>\n    </div>\n    <div class=\"section mistake\">\n      <div class=\"sec-head\"><span class=\"dot\"></span>❌ จุดที่พลาดบ่อย</div>\n      <ul>\n      <li>เอา \\(b\\) ไปคิดกับ SD</li>\n      <li>ลืมว่า mean เปลี่ยนทั้งคูณและบวก</li>\n      </ul>\n    </div>\n    <div class=\"section hack\">\n      <div class=\"sec-head\"><span class=\"dot\"></span>🧠 เทคนิคจำ</div>\n      <div class=\"txt\">\"Mean รับบวก SD ไม่รับบวก\"</div>\n    </div>\n    <div class=\"section examtip\">\n      <div class=\"sec-head\"><span class=\"dot\"></span>🎯 ข้อสอบชอบออก</div>\n      <p>ข้อสอบชอบให้สมการแปลงข้อมูลแล้วถาม mean, SD, variance พร้อมกัน ต้องแยกให้ชัดว่าค่ากลางเปลี่ยนตามสูตรตรงๆ แต่การกระจายดูแค่ \\(a\\) เท่านั้น</p>\n    </div>\n    <div class=\"section checklist\">\n      <div class=\"sec-head\"><span class=\"dot\"></span>☑ Before You Submit</div>\n      <ul>\n      <li>ระบุ \\(a\\) และ \\(b\\) ให้ชัด</li>\n      <li>เช็กว่า SD ต้องใช้ค่าสัมบูรณ์ของ \\(a\\)</li>\n      </ul>\n    </div>\n    <div class=\"pagefoot\">StatisticsRescue Kit · เปิดก่อนสอบ 10 นาที</div>\n  </div>\n\n\n  <div class=\"card\" data-accent=\"green\">\n    <div class=\"card-head\">\n      <div class=\"eyebrow\">PART 7 · Data Transformation · 🟢 Formula</div>\n      <div class=\"title\">ค่าเฉลี่ยใหม่</div>\n    </div>\n    <div class=\"trigger-box\">\n      <div class=\"ic\">🎯</div>\n      <div class=\"txt\">ค่ากลางเปลี่ยนตรงตามสมการเดิม</div>\n    </div>\n    <div class=\"section when\">\n      <div class=\"sec-head\"><span class=\"dot\"></span>👀 เมื่อเจอโจทย์แบบนี้</div>\n      <ul>\n      <li>รู้ \\(\\bar{x}\\) และโจทย์ให้ \\(y=ax+b\\)</li>\n      <li>ถามหา mean ใหม่หลังปรับคะแนน</li>\n      </ul>\n    </div>\n    <div class=\"section how\">\n      <div class=\"sec-head\"><span class=\"dot\"></span>✅ วิธีคิด</div>\n      <ol>\n      <li>ใช้ \\(\\bar{y}=a\\bar{x}+b\\)</li>\n      <li>แทนค่าแล้วคำนวณ</li>\n      <li>ตอบเป็นหน่วยเดิมของข้อมูลใหม่</li>\n      </ol>\n    </div>\n    <div class=\"section mistake\">\n      <div class=\"sec-head\"><span class=\"dot\"></span>❌ จุดที่พลาดบ่อย</div>\n      <ul>\n      <li>ใช้ \\(\\bar{y}=a(\\bar{x}+b)\\)</li>\n      <li>ลืมบวก \\(b\\) หลังคูณ</li>\n      </ul>\n    </div>\n    <div class=\"section hack\">\n      <div class=\"sec-head\"><span class=\"dot\"></span>🧠 เทคนิคจำ</div>\n      <div class=\"txt\">\"Mean = คูณก่อน บวกทีหลัง\"</div>\n    </div>\n    <div class=\"section examtip\">\n      <div class=\"sec-head\"><span class=\"dot\"></span>🎯 ข้อสอบชอบออก</div>\n      <p>โจทย์มักให้ค่าเฉลี่ยเดิมมาแล้วถามค่าเฉลี่ยใหม่จากการเลื่อนสเกล อย่าคิดแบบเดาสุ่ม เพราะ mean เปลี่ยนแบบตรงไปตรงมา</p>\n    </div>\n    <div class=\"section checklist\">\n      <div class=\"sec-head\"><span class=\"dot\"></span>☑ Before You Submit</div>\n      <ul>\n      <li>คูณ \\(\\bar{x}\\) ก่อน</li>\n      <li>แล้วค่อยบวก \\(b\\)</li>\n      </ul>\n    </div>\n    <div class=\"pagefoot\">StatisticsRescue Kit · เปิดก่อนสอบ 10 นาที</div>\n  </div>\n\n\n  <div class=\"card\" data-accent=\"orange\">\n    <div class=\"card-head\">\n      <div class=\"eyebrow\">PART 7 · Data Transformation · 🟢 Formula</div>\n      <div class=\"title\">ส่วนเบี่ยงเบนมาตรฐาน</div>\n    </div>\n    <div class=\"trigger-box\">\n      <div class=\"ic\">🎯</div>\n      <div class=\"txt\">SD สนแค่การคูณ บวกเท่าไรก็ไม่เปลี่ยน</div>\n    </div>\n    <div class=\"section when\">\n      <div class=\"sec-head\"><span class=\"dot\"></span>👀 เมื่อเจอโจทย์แบบนี้</div>\n      <ul>\n      <li>ข้อมูลถูกบวกค่าคงที่ทุกตัว</li>\n      <li>ข้อมูลถูกคูณด้วย \\(a\\)</li>\n      </ul>\n    </div>\n    <div class=\"section how\">\n      <div class=\"sec-head\"><span class=\"dot\"></span>✅ วิธีคิด</div>\n      <ol>\n      <li>ใช้ \\(SD_y=|a|SD_x\\)</li>\n      <li>ถ้ามีแต่บวก \\(b\\) ให้ SD เท่าเดิม</li>\n      <li>ถ้าคูณติดลบให้ใส่ค่าสัมบูรณ์</li>\n      </ol>\n    </div>\n    <div class=\"section mistake\">\n      <div class=\"sec-head\"><span class=\"dot\"></span>❌ จุดที่พลาดบ่อย</div>\n      <ul>\n      <li>เอา \\(b\\) ไปบวกกับ SD</li>\n      <li>ตอบ SD ติดลบ</li>\n      </ul>\n    </div>\n    <div class=\"section hack\">\n      <div class=\"sec-head\"><span class=\"dot\"></span>🧠 เทคนิคจำ</div>\n      <div class=\"txt\">\"SD จำแค่ |a|\"</div>\n    </div>\n    <div class=\"section examtip\">\n      <div class=\"sec-head\"><span class=\"dot\"></span>🎯 ข้อสอบชอบออก</div>\n      <p>ข้อสอบชอบหลอกด้วยการคูณเลขติดลบหรือบวกค่าคงที่ ถ้าคิดว่า SD เปลี่ยนทุกครั้งจะเสียแต้มทันที</p>\n    </div>\n    <div class=\"section checklist\">\n      <div class=\"sec-head\"><span class=\"dot\"></span>☑ Before You Submit</div>\n      <ul>\n      <li>ดูว่ามีแค่ \\(b\\) หรือไม่</li>\n      <li>เช็กค่าสัมบูรณ์ของ \\(a\\) ทุกครั้ง</li>\n      </ul>\n    </div>\n    <div class=\"pagefoot\">StatisticsRescue Kit · เปิดก่อนสอบ 10 นาที</div>\n  </div>\n\n\n  <div class=\"card\" data-accent=\"purple\">\n    <div class=\"card-head\">\n      <div class=\"eyebrow\">PART 7 · Data Transformation · 🟢 Formula</div>\n      <div class=\"title\">ความแปรปรวน</div>\n    </div>\n    <div class=\"trigger-box\">\n      <div class=\"ic\">🎯</div>\n      <div class=\"txt\">Variance แรงกว่า SD เพราะยกกำลังสอง</div>\n    </div>\n    <div class=\"section when\">\n      <div class=\"sec-head\"><span class=\"dot\"></span>👀 เมื่อเจอโจทย์แบบนี้</div>\n      <ul>\n      <li>ถามหา \\(Var\\) หลังแปลงข้อมูล</li>\n      <li>มีการคูณด้วย \\(a\\)</li>\n      </ul>\n    </div>\n    <div class=\"section how\">\n      <div class=\"sec-head\"><span class=\"dot\"></span>✅ วิธีคิด</div>\n      <ol>\n      <li>ใช้ \\(Var_y=a^2Var_x\\)</li>\n      <li>จำว่า \\(Var=SD^2\\)</li>\n      <li>ตัวคูณต้องยกกำลังสอง</li>\n      </ol>\n    </div>\n    <div class=\"section mistake\">\n      <div class=\"sec-head\"><span class=\"dot\"></span>❌ จุดที่พลาดบ่อย</div>\n      <ul>\n      <li>ใช้ \\(a\\) แค่ตัวเดียว</li>\n      <li>ลืมว่า variance ไม่สน \\(b\\)</li>\n      </ul>\n    </div>\n    <div class=\"section hack\">\n      <div class=\"sec-head\"><span class=\"dot\"></span>🧠 เทคนิคจำ</div>\n      <div class=\"txt\">\"Variance = a² เท่านั้น\"</div>\n    </div>\n    <div class=\"section examtip\">\n      <div class=\"sec-head\"><span class=\"dot\"></span>🎯 ข้อสอบชอบออก</div>\n      <p>ถ้าข้อสอบให้หา variance จากการแปลงเชิงเส้น ให้รีบยก \\(a\\) เป็นกำลังสองก่อนคิดต่อ มักออกคู่กับ SD เสมอ</p>\n    </div>\n    <div class=\"section checklist\">\n      <div class=\"sec-head\"><span class=\"dot\"></span>☑ Before You Submit</div>\n      <ul>\n      <li>เขียน \\(a^2\\) ให้ครบ</li>\n      <li>ไม่เอา \\(b\\) มาปน</li>\n      </ul>\n    </div>\n    <div class=\"pagefoot\">StatisticsRescue Kit · เปิดก่อนสอบ 10 นาที</div>\n  </div>"
    },
    {
      "id": "stat-p8",
      "num": "PART 8",
      "name": "Distribution Shape",
      "th": "Distribution Shape",
      "cardCount": 3,
      "accent": "#9333ea",
      "gridHTML": "<div class=\"card\" data-accent=\"blue\">\n    <div class=\"card-head\">\n      <div class=\"eyebrow\">PART 8 · Distribution Shape · 🔵 Concept</div>\n      <div class=\"title\">กราฟสมมาตร</div>\n    </div>\n    <div class=\"trigger-box\">\n      <div class=\"ic\">🎯</div>\n      <div class=\"txt\">กราฟเท่ากันสองข้าง ค่ากลางชนกัน</div>\n    </div>\n    <div class=\"section when\">\n      <div class=\"sec-head\"><span class=\"dot\"></span>👀 เมื่อเจอโจทย์แบบนี้</div>\n      <ul>\n      <li>กราฟโค้งซ้ายขวาเท่ากัน</li>\n      <li>ข้อมูลกระจายสมดุล</li>\n      </ul>\n    </div>\n    <div class=\"section how\">\n      <div class=\"sec-head\"><span class=\"dot\"></span>✅ วิธีคิด</div>\n      <ol>\n      <li>ดูว่ารูปซ้ายขวาใกล้กัน</li>\n      <li>สรุป \\(Mean=Median=Mode\\)</li>\n      <li>ใช้กับกราฟระฆังคว่ำสวยๆ</li>\n      </ol>\n    </div>\n    <div class=\"section mistake\">\n      <div class=\"sec-head\"><span class=\"dot\"></span>❌ จุดที่พลาดบ่อย</div>\n      <ul>\n      <li>คิดว่าระฆังคว่ำคือเบ้</li>\n      <li>จำลำดับค่ากลางผิด</li>\n      </ul>\n    </div>\n    <div class=\"section hack\">\n      <div class=\"sec-head\"><span class=\"dot\"></span>🧠 เทคนิคจำ</div>\n      <div class=\"txt\">\"สมมาตร = สามค่าเท่ากัน\"</div>\n    </div>\n    <div class=\"section examtip\">\n      <div class=\"sec-head\"><span class=\"dot\"></span>🎯 ข้อสอบชอบออก</div>\n      <p>ข้อสอบชอบให้รูปกราฟมาแล้วถามแปลผลจากตำแหน่งค่ากลาง ถ้ากราฟสมดุลจริง ให้ตอบสามค่าเท่ากันได้เลย</p>\n    </div>\n    <div class=\"section checklist\">\n      <div class=\"sec-head\"><span class=\"dot\"></span>☑ Before You Submit</div>\n      <ul>\n      <li>ดูซ้ายขวาเท่ากันไหม</li>\n      <li>เช็กสามค่ากลางให้ตรงกัน</li>\n      </ul>\n    </div>\n    <div class=\"pagefoot\">StatisticsRescue Kit · เปิดก่อนสอบ 10 นาที</div>\n  </div>\n\n\n  <div class=\"card\" data-accent=\"green\">\n    <div class=\"card-head\">\n      <div class=\"eyebrow\">PART 8 · Distribution Shape · 🔵 Concept</div>\n      <div class=\"title\">กราฟเบ้ขวา</div>\n    </div>\n    <div class=\"trigger-box\">\n      <div class=\"ic\">🎯</div>\n      <div class=\"txt\">หางยาวขวา Mean ถูกดึงไปทางขวา</div>\n    </div>\n    <div class=\"section when\">\n      <div class=\"sec-head\"><span class=\"dot\"></span>👀 เมื่อเจอโจทย์แบบนี้</div>\n      <ul>\n      <li>คะแนนส่วนใหญ่ต่ำแต่มีบางค่าสูงมาก</li>\n      <li>กราฟหางยื่นไปทางขวา</li>\n      </ul>\n    </div>\n    <div class=\"section how\">\n      <div class=\"sec-head\"><span class=\"dot\"></span>✅ วิธีคิด</div>\n      <ol>\n      <li>จำลำดับ \\(Mean>Median>Mode\\)</li>\n      <li>มองหาค่าสุดโต่งด้านขวา</li>\n      <li>ตีความว่า mean ถูกลากขึ้น</li>\n      </ol>\n    </div>\n    <div class=\"section mistake\">\n      <div class=\"sec-head\"><span class=\"dot\"></span>❌ จุดที่พลาดบ่อย</div>\n      <ul>\n      <li>สลับเป็นเบ้ซ้าย</li>\n      <li>คิดว่าหางขวาแปลว่าคนได้สูงเยอะ</li>\n      </ul>\n    </div>\n    <div class=\"section hack\">\n      <div class=\"sec-head\"><span class=\"dot\"></span>🧠 เทคนิคจำ</div>\n      <div class=\"txt\">\"หางขวา Mean นำ\"</div>\n    </div>\n    <div class=\"section examtip\">\n      <div class=\"sec-head\"><span class=\"dot\"></span>🎯 ข้อสอบชอบออก</div>\n      <p>โจทย์กราฟเบ้ขวามักมีค่าบางตัวสูงมากจนดัน mean สูงกว่าค่าอื่น อย่าเผลอใช้ median แทน mean ตอนแปลผล</p>\n    </div>\n    <div class=\"section checklist\">\n      <div class=\"sec-head\"><span class=\"dot\"></span>☑ Before You Submit</div>\n      <ul>\n      <li>ดูหางไปทางขวาไหม</li>\n      <li>เรียง \\(Mean, Median, Mode\\) ให้ถูก</li>\n      </ul>\n    </div>\n    <div class=\"pagefoot\">StatisticsRescue Kit · เปิดก่อนสอบ 10 นาที</div>\n  </div>\n\n\n  <div class=\"card\" data-accent=\"orange\">\n    <div class=\"card-head\">\n      <div class=\"eyebrow\">PART 8 · Distribution Shape · 🔵 Concept</div>\n      <div class=\"title\">กราฟเบ้ซ้าย</div>\n    </div>\n    <div class=\"trigger-box\">\n      <div class=\"ic\">🎯</div>\n      <div class=\"txt\">หางยาวซ้าย Mean ถูกดึงไปทางซ้าย</div>\n    </div>\n    <div class=\"section when\">\n      <div class=\"sec-head\"><span class=\"dot\"></span>👀 เมื่อเจอโจทย์แบบนี้</div>\n      <ul>\n      <li>คะแนนส่วนใหญ่สูงแต่มีบางค่าต่ำมาก</li>\n      <li>กราฟหางยื่นไปทางซ้าย</li>\n      </ul>\n    </div>\n    <div class=\"section how\">\n      <div class=\"sec-head\"><span class=\"dot\"></span>✅ วิธีคิด</div>\n      <ol>\n      <li>จำลำดับ \\(Mean<Median<Mode\\)</li>\n      <li>นึกว่าค่าสุดโต่งอยู่ซ้าย</li>\n      <li>ตีความว่า mean ถูกลากลง</li>\n      </ol>\n    </div>\n    <div class=\"section mistake\">\n      <div class=\"sec-head\"><span class=\"dot\"></span>❌ จุดที่พลาดบ่อย</div>\n      <ul>\n      <li>สลับกับเบ้ขวา</li>\n      <li>คิดว่าหางซ้ายแปลว่าคนได้ต่ำเยอะ</li>\n      </ul>\n    </div>\n    <div class=\"section hack\">\n      <div class=\"sec-head\"><span class=\"dot\"></span>🧠 เทคนิคจำ</div>\n      <div class=\"txt\">\"หางซ้าย Mean ตามหลัง\"</div>\n    </div>\n    <div class=\"section examtip\">\n      <div class=\"sec-head\"><span class=\"dot\"></span>🎯 ข้อสอบชอบออก</div>\n      <p>ข้อสอบชอบให้ดูฮิสโทแกรมหรือ box plot แล้วสรุปการเบ้ ถ้าหางซ้ายยาวให้จำว่า mean มักน้อยสุดในสามค่า</p>\n    </div>\n    <div class=\"section checklist\">\n      <div class=\"sec-head\"><span class=\"dot\"></span>☑ Before You Submit</div>\n      <ul>\n      <li>ดูหางไปทางซ้ายไหม</li>\n      <li>เช็ก \\(Mean<Median<Mode\\)</li>\n      </ul>\n    </div>\n    <div class=\"pagefoot\">StatisticsRescue Kit · เปิดก่อนสอบ 10 นาที</div>\n  </div>"
    },
    {
      "id": "stat-p9",
      "num": "PART 9",
      "name": "Ultimate Exam Rescue",
      "th": "Ultimate Exam Rescue",
      "cardCount": 4,
      "accent": "#9333ea",
      "gridHTML": "<div class=\"card\" data-accent=\"blue\">\n    <div class=\"card-head\">\n      <div class=\"eyebrow\">PART 9 · Ultimate Exam Rescue · 🟢 Formula</div>\n      <div class=\"title\">ค่าเฉลี่ยรวม</div>\n    </div>\n    <div class=\"trigger-box\">\n      <div class=\"ic\">🎯</div>\n      <div class=\"txt\">เฉลี่ยรวมต้องถ่วงด้วยจำนวนคน</div>\n    </div>\n    <div class=\"section when\">\n      <div class=\"sec-head\"><span class=\"dot\"></span>👀 เมื่อเจอโจทย์แบบนี้</div>\n      <ul>\n      <li>มี 2 กลุ่มข้อมูล</li>\n      <li>รู้ \\(N_1, \\bar{x}_1, N_2, \\bar{x}_2\\)</li>\n      </ul>\n    </div>\n    <div class=\"section how\">\n      <div class=\"sec-head\"><span class=\"dot\"></span>✅ วิธีคิด</div>\n      <ol>\n      <li>ใช้ \\(\\bar{x}_{รวม}=\\frac{N_1\\bar{x}_1+N_2\\bar{x}_2}{N_1+N_2}\\)</li>\n      <li>คูณแต่ละกลุ่มด้วยจำนวนคน</li>\n      <li>แล้วหารด้วยจำนวนรวม</li>\n      </ol>\n    </div>\n    <div class=\"section mistake\">\n      <div class=\"sec-head\"><span class=\"dot\"></span>❌ จุดที่พลาดบ่อย</div>\n      <ul>\n      <li>เอา mean มาบวกตรงๆ</li>\n      <li>ลืมถ่วงน้ำหนักด้วย \\(N\\)</li>\n      </ul>\n    </div>\n    <div class=\"section hack\">\n      <div class=\"sec-head\"><span class=\"dot\"></span>🧠 เทคนิคจำ</div>\n      <div class=\"txt\">\"รวมเฉลี่ย = ถ่วงน้ำหนัก\"</div>\n    </div>\n    <div class=\"section examtip\">\n      <div class=\"sec-head\"><span class=\"dot\"></span>🎯 ข้อสอบชอบออก</div>\n      <p>ข้อสอบรวมสองกลุ่มชอบหลอกให้บวก mean ตรงๆ แต่คำตอบที่ถูกต้องต้องถ่วงด้วยจำนวนข้อมูลเสมอ ยกเว้นจำนวนคนเท่ากัน</p>\n    </div>\n    <div class=\"section checklist\">\n      <div class=\"sec-head\"><span class=\"dot\"></span>☑ Before You Submit</div>\n      <ul>\n      <li>เช็กจำนวนคนแต่ละกลุ่ม</li>\n      <li>อย่าลืมคูณ mean ด้วย \\(N\\)</li>\n      </ul>\n    </div>\n    <div class=\"pagefoot\">StatisticsRescue Kit · เปิดก่อนสอบ 10 นาที</div>\n  </div>\n\n\n  <div class=\"card\" data-accent=\"green\">\n    <div class=\"card-head\">\n      <div class=\"eyebrow\">PART 9 · Ultimate Exam Rescue · 🟠 Trigger</div>\n      <div class=\"title\">จำนวนเท่ากัน</div>\n    </div>\n    <div class=\"trigger-box\">\n      <div class=\"ic\">🎯</div>\n      <div class=\"txt\">คนเท่ากัน เอา mean เฉลี่ยกันได้เลย</div>\n    </div>\n    <div class=\"section when\">\n      <div class=\"sec-head\"><span class=\"dot\"></span>👀 เมื่อเจอโจทย์แบบนี้</div>\n      <ul>\n      <li>สองกลุ่มมี \\(N\\) เท่ากัน</li>\n      <li>ถามค่าเฉลี่ยรวมแบบเร็ว</li>\n      </ul>\n    </div>\n    <div class=\"section how\">\n      <div class=\"sec-head\"><span class=\"dot\"></span>✅ วิธีคิด</div>\n      <ol>\n      <li>ถ้า \\(N_1=N_2\\)</li>\n      <li>ใช้ \\(\\bar{x}_{รวม}=\\frac{\\bar{x}_1+\\bar{x}_2}{2}\\)</li>\n      <li>ไม่ต้องเขียนสูตรยาว</li>\n      </ol>\n    </div>\n    <div class=\"section mistake\">\n      <div class=\"sec-head\"><span class=\"dot\"></span>❌ จุดที่พลาดบ่อย</div>\n      <ul>\n      <li>ยังคงถ่วงน้ำหนักซ้ำๆ</li>\n      <li>ลืมเช็กว่า \\(N\\) เท่ากันจริง</li>\n      </ul>\n    </div>\n    <div class=\"section hack\">\n      <div class=\"sec-head\"><span class=\"dot\"></span>🧠 เทคนิคจำ</div>\n      <div class=\"txt\">\"คนเท่ากัน ใช้ค่าเฉลี่ยของ mean\"</div>\n    </div>\n    <div class=\"section examtip\">\n      <div class=\"sec-head\"><span class=\"dot\"></span>🎯 ข้อสอบชอบออก</div>\n      <p>เป็นทริกที่ชอบออกในข้อสั้นๆ ถ้าจำนวนคนสองกลุ่มเท่ากันจริง สามารถย่อการคิดได้ทันทีและลดความผิดพลาด</p>\n    </div>\n    <div class=\"section checklist\">\n      <div class=\"sec-head\"><span class=\"dot\"></span>☑ Before You Submit</div>\n      <ul>\n      <li>ยืนยันว่า \\(N_1=N_2\\)</li>\n      <li>ค่อยใช้ค่าเฉลี่ยของสอง mean</li>\n      </ul>\n    </div>\n    <div class=\"pagefoot\">StatisticsRescue Kit · เปิดก่อนสอบ 10 นาที</div>\n  </div>\n\n\n  <div class=\"card\" data-accent=\"orange\">\n    <div class=\"card-head\">\n      <div class=\"eyebrow\">PART 9 · Ultimate Exam Rescue · 🔵 Concept</div>\n      <div class=\"title\">ข้อมูลเท่ากันหมด</div>\n    </div>\n    <div class=\"trigger-box\">\n      <div class=\"ic\">🎯</div>\n      <div class=\"txt\">ไม่มีการกระจาย SD และ Variance เป็นศูนย์</div>\n    </div>\n    <div class=\"section when\">\n      <div class=\"sec-head\"><span class=\"dot\"></span>👀 เมื่อเจอโจทย์แบบนี้</div>\n      <ul>\n      <li>ข้อมูลทุกตัวเป็นค่าเดียวกัน</li>\n      <li>เช่น \\(5,5,5,5\\)</li>\n      </ul>\n    </div>\n    <div class=\"section how\">\n      <div class=\"sec-head\"><span class=\"dot\"></span>✅ วิธีคิด</div>\n      <ol>\n      <li>ดูว่าค่าทุกตัวเท่ากัน</li>\n      <li>สรุป \\(SD=0\\)</li>\n      <li>สรุป \\(Var=0\\)</li>\n      </ol>\n    </div>\n    <div class=\"section mistake\">\n      <div class=\"sec-head\"><span class=\"dot\"></span>❌ จุดที่พลาดบ่อย</div>\n      <ul>\n      <li>คิดว่า SD ยังบวกได้</li>\n      <li>ลืมว่าไม่มีความกระจาย</li>\n      </ul>\n    </div>\n    <div class=\"section hack\">\n      <div class=\"sec-head\"><span class=\"dot\"></span>🧠 เทคนิคจำ</div>\n      <div class=\"txt\">\"เหมือนกันหมด = กระจายศูนย์\"</div>\n    </div>\n    <div class=\"section examtip\">\n      <div class=\"sec-head\"><span class=\"dot\"></span>🎯 ข้อสอบชอบออก</div>\n      <p>ถ้าชุดข้อมูลทุกตัวเท่ากัน ข้อสอบมักถาม SD หรือ variance เพื่อเช็กว่ารู้ความหมายของการกระจายจริงหรือไม่ คำตอบต้องเป็นศูนย์</p>\n    </div>\n    <div class=\"section checklist\">\n      <div class=\"sec-head\"><span class=\"dot\"></span>☑ Before You Submit</div>\n      <ul>\n      <li>ดูว่าค่าซ้ำหมดไหม</li>\n      <li>ตอบ \\(SD=0\\) และ \\(Var=0\\)</li>\n      </ul>\n    </div>\n    <div class=\"pagefoot\">StatisticsRescue Kit · เปิดก่อนสอบ 10 นาที</div>\n  </div>\n\n\n  <div class=\"card\" data-accent=\"purple\">\n    <div class=\"card-head\">\n      <div class=\"eyebrow\">PART 9 · Ultimate Exam Rescue · 🟣 Exam Tip</div>\n      <div class=\"title\">เช็กก่อนส่ง</div>\n    </div>\n    <div class=\"trigger-box\">\n      <div class=\"ic\">🎯</div>\n      <div class=\"txt\">เรียงข้อมูลก่อนหา median ใช้สูตร SD ให้ถูกชุด</div>\n    </div>\n    <div class=\"section when\">\n      <div class=\"sec-head\"><span class=\"dot\"></span>👀 เมื่อเจอโจทย์แบบนี้</div>\n      <ul>\n      <li>ต้องหา median หรือ quartile</li>\n      <li>ต้องเลือกสูตร SD ระหว่าง \\(N\\) กับ \\(N-1\\)</li>\n      </ul>\n    </div>\n    <div class=\"section how\">\n      <div class=\"sec-head\"><span class=\"dot\"></span>✅ วิธีคิด</div>\n      <ol>\n      <li>เรียงข้อมูลจากน้อยไปมากก่อน</li>\n      <li>เช็กว่าใช้ประชากรหรือกลุ่มตัวอย่าง</li>\n      <li>ทวนสูตรอีกครั้งก่อนส่ง</li>\n      </ol>\n    </div>\n    <div class=\"section mistake\">\n      <div class=\"sec-head\"><span class=\"dot\"></span>❌ จุดที่พลาดบ่อย</div>\n      <ul>\n      <li>หา quartile จากข้อมูลไม่เรียง</li>\n      <li>ใช้ \\(N\\) ผิดสถานการณ์</li>\n      </ul>\n    </div>\n    <div class=\"section hack\">\n      <div class=\"sec-head\"><span class=\"dot\"></span>🧠 เทคนิคจำ</div>\n      <div class=\"txt\">\"เรียงก่อน ค่อยหากึ่งกลาง\"</div>\n    </div>\n    <div class=\"section examtip\">\n      <div class=\"sec-head\"><span class=\"dot\"></span>🎯 ข้อสอบชอบออก</div>\n      <p>ข้อสอบชอบให้ข้อมูลไม่เรียงมาแล้วถาม median หรือ quartile ถ้าไม่เรียงก่อนจะพลาดทันที อีกจุดคือแยกสูตร SD ของประชากรกับตัวอย่างให้ชัด</p>\n    </div>\n    <div class=\"section checklist\">\n      <div class=\"sec-head\"><span class=\"dot\"></span>☑ Before You Submit</div>\n      <ul>\n      <li>เรียงข้อมูลแล้วหรือยัง</li>\n      <li>ใช้ \\(N\\) หรือ \\(N-1\\) ถูกไหม</li>\n      </ul>\n    </div>\n    <div class=\"pagefoot\">StatisticsRescue Kit · เปิดก่อนสอบ 10 นาที</div>\n  </div>"
    }
  ]
}